{"legendLength":5,"data":[{"index":0,"showInLegend":false,"name":"Skoky na lyžích + Severská kombinace","data":[]},{"index":1,"showInLegend":false,"name":"Boby","data":[]},{"index":2,"showInLegend":true,"name":"Krasobruslení","data":[{"name":"Zsuzsa Almssy","y":158,"x":60,"t":"HUN","custom":"Krasobruslení"},{"name":"Lyudmila Yevgenevna Belousova (-Protopopova)","y":160,"x":46,"t":"URS","custom":"Krasobruslení"},{"name":"Petra Burka","y":153,"x":60,"t":"CAN","custom":"Krasobruslení"},{"name":"Diana Cynthia Clifton-Peach (-Stevens)","y":160,"x":52,"t":"GBR","custom":"Krasobruslení"},{"name":"Sjoukje Rosalinde Dijkstra (-Kossmayer)","y":169,"x":54,"t":"NED","custom":"Krasobruslení"},{"name":"Peggy Gale Fleming (-Jenkins)","y":163,"x":50,"t":"USA","custom":"Krasobruslení"},{"name":"Judianne \"Judi\" Fotheringill (-Fuller)","y":170,"x":57,"t":"USA","custom":"Krasobruslení"},{"name":"Ann-Margreth Frei-Kck (-Hall)","y":155,"x":52,"t":"SWE","custom":"Krasobruslení"},{"name":"Miwa Fukuhara","y":156,"x":52,"t":"JPN","custom":"Krasobruslení"},{"name":"Wendy Elizabeth Griner (-Ballantyne)","y":156,"x":56,"t":"CAN","custom":"Krasobruslení"},{"name":"Christine Haigler (-Krall)","y":162,"x":52,"t":"USA","custom":"Krasobruslení"},{"name":"Nicole Hassler","y":157,"x":47,"t":"FRA","custom":"Krasobruslení"},{"name":"Berit Unn Sandvik Johansen (-Sissener)","y":167,"x":57,"t":"NOR","custom":"Krasobruslení"},{"name":"Gerda Johner","y":161,"x":53,"t":"SUI","custom":"Krasobruslení"},{"name":"Vivian Laureen Joseph","y":159,"x":57,"t":"USA","custom":"Krasobruslení"},{"name":"Cynthia Diane \"Cindy\" Kauffman (-Marshall)","y":160,"x":49,"t":"USA","custom":"Krasobruslení"},{"name":"Shirra Kenworthy","y":162,"x":58,"t":"CAN","custom":"Krasobruslení"},{"name":"Ursula \"Uschi\" Keler (-Keszler)","y":168,"x":47,"t":"GER","custom":"Krasobruslení"},{"name":"Marika Kilius (-Zahn, -Schfer)","y":168,"x":51,"t":"GER","custom":"Krasobruslení"},{"name":"Hana Makov","y":168,"x":58,"t":"TCH","custom":"Krasobruslení"},{"name":"Albertina Natalie \"Tina\" Noyes","y":160,"x":52,"t":"USA","custom":"Krasobruslení"},{"name":"Kumiko Okawa (-Sato)","y":157,"x":53,"t":"JPN","custom":"Krasobruslení"},{"name":"Inge Paul","y":160,"x":50,"t":"GER","custom":"Krasobruslení"},{"name":"Margit Senf","y":170,"x":62,"t":"GER","custom":"Krasobruslení"},{"name":"Helene \"Helli\" Sengstschmid (-Tunner)","y":167,"x":57,"t":"AUT","custom":"Krasobruslení"},{"name":"Gabriele Seyfert (-Rger, -Messerschmidt, -Krner)","y":160,"x":47,"t":"GER","custom":"Krasobruslení"},{"name":"Sally-Anne Martine Stapleford","y":162,"x":54,"t":"GBR","custom":"Krasobruslení"},{"name":"Ingeborg \"Inge\" Strell","y":155,"x":50,"t":"AUT","custom":"Krasobruslení"},{"name":"Faye Strutt (-Marshall)","y":154,"x":54,"t":"CAN","custom":"Krasobruslení"},{"name":"Junko Ueno (-Hiramata)","y":164,"x":56,"t":"JPN","custom":"Krasobruslení"},{"name":"Linda Ward (-Purdy)","y":154,"x":58,"t":"CAN","custom":"Krasobruslení"},{"name":"Carol-Ann Warner","y":164,"x":56,"t":"GBR","custom":"Krasobruslení"},{"name":"Deborah \"Debbi\" Wilkes (-Darroch)","y":160,"x":57,"t":"CAN","custom":"Krasobruslení"},{"name":"Brigitte Wokoeck","y":164,"x":56,"t":"GER","custom":"Krasobruslení"},{"name":"Tatyana Alekseyevna Zhuk (-Shesternyova, -Sokolova)","y":156,"x":52,"t":"URS","custom":"Krasobruslení"},{"name":"Monika Zingg","y":168,"x":56,"t":"SUI","custom":"Krasobruslení"}]},{"index":3,"showInLegend":true,"name":"Rychlobruslení + Short track","data":[{"name":"Jeanne Chesley Ashworth (-Walker-)","y":157,"x":57,"t":"USA","custom":"Rychlobruslení"},{"name":"Sigrit Behrenz","y":164,"x":66,"t":"GER","custom":"Rychlobruslení"},{"name":"Rita Blankenburg (-Schmidt)","y":162,"x":59,"t":"GER","custom":"Rychlobruslení"},{"name":"Inger Astrid Eriksson (-Hilding)","y":175,"x":67,"t":"SWE","custom":"Rychlobruslení"},{"name":"Helga Haase (Obschernitzki-)","y":160,"x":64,"t":"GER","custom":"Rychlobruslení"},{"name":"Han Pil-Hwa","y":170,"x":61,"t":"PRK","custom":"Rychlobruslení"},{"name":"Erika Heinicke (-Pflger)","y":166,"x":60,"t":"GER","custom":"Rychlobruslení"},{"name":"Kornlia Ihsz (Magyar -)","y":160,"x":61,"t":"HUN","custom":"Rychlobruslení"},{"name":"Gunilla Gerd Irene Jacobsson (-Sjstrm)","y":170,"x":65,"t":"SWE","custom":"Rychlobruslení"},{"name":"Kaija-Liisa Keskivitikka","y":172,"x":68,"t":"FIN","custom":"Rychlobruslení"},{"name":"Kim Gwi-Jin","y":165,"x":62,"t":"KOR","custom":"Rychlobruslení"},{"name":"Kim Song-Soon","y":158,"x":63,"t":"PRK","custom":"Rychlobruslení"},{"name":"Janice Marie \"Mary\" Lawler","y":162,"x":59,"t":"USA","custom":"Rychlobruslení"},{"name":"Inge Lieckfeldt","y":160,"x":56,"t":"GER","custom":"Rychlobruslení"},{"name":"Sigrid Christina Lindblom-Scherling","y":159,"x":62,"t":"SWE","custom":"Rychlobruslení"},{"name":"Barbara Day \"Barb\" Lockhart","y":171,"x":66,"t":"USA","custom":"Rychlobruslení"},{"name":"Franoise Lucas","y":168,"x":62,"t":"FRA","custom":"Rychlobruslení"},{"name":"Doreen Ann McCannell (-Botterill)","y":167,"x":58,"t":"CAN","custom":"Rychlobruslení"},{"name":"Judith Helen \"Judy\" Morstein (-Martz)","y":176,"x":68,"t":"USA","custom":"Rychlobruslení"},{"name":"Adelajda Mroske (-abul)","y":162,"x":60,"t":"POL","custom":"Rychlobruslení"},{"name":"Kaija Marja Mustonen","y":166,"x":53,"t":"FIN","custom":"Rychlobruslení"},{"name":"Hatsue Nagakubo-Takamizawa","y":153,"x":50,"t":"JPN","custom":"Rychlobruslení"},{"name":"Helena Pilejczyk (Majcher-)","y":159,"x":51,"t":"POL","custom":"Rychlobruslení"},{"name":"Brigitte Reichert","y":152,"x":59,"t":"GER","custom":"Rychlobruslení"},{"name":"Doreen Delores Ryan (McLeod-)","y":170,"x":73,"t":"CAN","custom":"Rychlobruslení"},{"name":"Ryoo Choon-Za","y":157,"x":59,"t":"PRK","custom":"Rychlobruslení"},{"name":"Elwira Teresa Seroczyska (Potapowicz-)","y":160,"x":59,"t":"POL","custom":"Rychlobruslení"},{"name":"Lidiya Pavlovna Skoblikova (-Polozkova)","y":163,"x":59,"t":"URS","custom":"Rychlobruslení"},{"name":"Janice Marie \"Jan\" Smith","y":169,"x":66,"t":"USA","custom":"Rychlobruslení"},{"name":"Valentina Sergeyevna Stenina (Miloslavova-)","y":154,"x":52,"t":"URS","custom":"Rychlobruslení"},{"name":"Kaneko Takahashi","y":163,"x":60,"t":"JPN","custom":"Rychlobruslení"},{"name":"Yasuko Takano","y":152,"x":52,"t":"JPN","custom":"Rychlobruslení"},{"name":"Sylvia Josephine White (-Blaine)","y":162,"x":59,"t":"USA","custom":"Rychlobruslení"},{"name":"Irina Nikolayevna Yegorova (-Pavlova)","y":167,"x":65,"t":"URS","custom":"Rychlobruslení"}]},{"index":4,"showInLegend":true,"name":"Běh na lyžích + Biatlon","data":[{"name":"Rita Nikolayevna Achkina","y":168,"x":63,"t":"URS","custom":"Běh na lyžích"},{"name":"Gun Margareta del (-Nilsson)","y":163,"x":52,"t":"SWE","custom":"Běh na lyžích"},{"name":"va Balzs (-Ozse)","y":172,"x":67,"t":"HUN","custom":"Běh na lyžích"},{"name":"Stefania Biegun","y":160,"x":60,"t":"POL","custom":"Běh na lyžích"},{"name":"Klavdiya Sergeyevna Boyarskikh","y":159,"x":60,"t":"URS","custom":"Běh na lyžích"},{"name":"Weronika Krystyna Budny (Stempak-)","y":163,"x":53,"t":"POL","custom":"Běh na lyžích"},{"name":"Rita Czech-Blasel","y":174,"x":68,"t":"GER","custom":"Běh na lyžích"},{"name":"Renate Dannhauer-Borges","y":166,"x":53,"t":"GER","custom":"Běh na lyžích"},{"name":"Roza Dimova (-Peneva)","y":168,"x":60,"t":"BUL","custom":"Běh na lyžích"},{"name":"Mariya Ivanovna Gusakova (Kudimova-)","y":159,"x":59,"t":"URS","custom":"Běh na lyžích"},{"name":"Toini Gustafsson (Karvonen-, -Rnnlund)","y":162,"x":54,"t":"SWE","custom":"Běh na lyžích"},{"name":"Katalin Hemrik (Hellner-)","y":163,"x":58,"t":"HUN","custom":"Běh na lyžích"},{"name":"Kim Bong-Za","y":160,"x":58,"t":"PRK","custom":"Běh na lyžích"},{"name":"Alevtina Pavlovna Kolchina (Leontyeva-)","y":162,"x":56,"t":"URS","custom":"Běh na lyžích"},{"name":"Mirja Annikki Lehtonen (-Kierros)","y":165,"x":54,"t":"FIN","custom":"Běh na lyžích"},{"name":"Barbro Martinsson (-Grahn)","y":172,"x":62,"t":"SWE","custom":"Běh na lyžích"},{"name":"Nadezhda Mikhaylova","y":168,"x":67,"t":"BUL","custom":"Běh na lyžích"},{"name":"Christine Nestler (Sldner-)","y":161,"x":60,"t":"GER","custom":"Běh na lyžích"},{"name":"Toini Kylikki Pysti (Mikkola-)","y":162,"x":53,"t":"FIN","custom":"Běh na lyžích"},{"name":"Senja Anneli Pusula (-Nuolikivi)","y":162,"x":52,"t":"FIN","custom":"Běh na lyžích"},{"name":"Ri Han-Soon","y":157,"x":58,"t":"PRK","custom":"Běh na lyžích"},{"name":"Eeva Ruoppa (Saarainen-)","y":162,"x":54,"t":"FIN","custom":"Běh na lyžích"},{"name":"Elfriede Spiegelhauer-Uhlig","y":168,"x":65,"t":"GER","custom":"Běh na lyžích"},{"name":"Krastana Stoeva","y":178,"x":69,"t":"BUL","custom":"Běh na lyžích"},{"name":"Britt Marianne Strandberg (-Lundn)","y":167,"x":60,"t":"SWE","custom":"Běh na lyžích"},{"name":"Mria Tarnai (Geczo-)","y":156,"x":56,"t":"HUN","custom":"Běh na lyžích"},{"name":"Teresa Jzefa Trzebunia","y":155,"x":54,"t":"POL","custom":"Běh na lyžích"},{"name":"Nadezhda Vasileva","y":165,"x":60,"t":"BUL","custom":"Běh na lyžích"}]},{"index":5,"showInLegend":false,"name":"Lední hokej","data":[]},{"index":6,"showInLegend":true,"name":"Alpské lyžování","data":[{"name":"Ruth Adolf","y":165,"x":56,"t":"SUI","custom":"Alpské lyžování"},{"name":"Majda Ankele (-Samaluk)","y":167,"x":60,"t":"YUG","custom":"Alpské lyžování"},{"name":"Anna Margaret Clark Asheshov","y":165,"x":64,"t":"GBR","custom":"Alpské lyžování"},{"name":"Lidia Barbieri Sacconaghi","y":170,"x":55,"t":"ITA","custom":"Alpské lyžování"},{"name":"Heidi Biebl (-Schmid, -Prelevi)","y":159,"x":56,"t":"GER","custom":"Alpské lyžování"},{"name":"Fernande Bochatay (-Frank)","y":163,"x":57,"t":"SUI","custom":"Alpské lyžování"},{"name":"Madeleine Bochatay (-Montessuit)","y":169,"x":60,"t":"FRA","custom":"Alpské lyžování"},{"name":"Linda Crutchfield-Bocock","y":164,"x":68,"t":"CAN","custom":"Alpské lyžování"},{"name":"Giustina Demetz","y":163,"x":55,"t":"ITA","custom":"Alpské lyžování"},{"name":"Stalina Sergeyevna Demidova-Korzukhina","y":158,"x":58,"t":"URS","custom":"Alpské lyžování"},{"name":"Karen Dokka (-Vageletos)","y":164,"x":61,"t":"CAN","custom":"Alpské lyžování"},{"name":"Anne-Marie \"Annie\" Famose (-Bremont)","y":158,"x":50,"t":"FRA","custom":"Alpské lyžování"},{"name":"Burgl Frbinger (-Leo)","y":172,"x":63,"t":"GER","custom":"Alpské lyžování"},{"name":"Barbara Hale Ferries (-Henderson)","y":166,"x":55,"t":"USA","custom":"Alpské lyžování"},{"name":"Divina Mary Galica","y":172,"x":60,"t":"GBR","custom":"Alpské lyžování"},{"name":"Maria Gsienica Daniel-Szatkowska","y":159,"x":55,"t":"POL","custom":"Alpské lyžování"},{"name":"Franoise Gay","y":160,"x":62,"t":"SUI","custom":"Alpské lyžování"},{"name":"Jane Eleanor Gissing","y":164,"x":63,"t":"GBR","custom":"Alpské lyžování"},{"name":"Christine Marion Elisabeth Goitschel (-Branger)","y":172,"x":62,"t":"FRA","custom":"Alpské lyžování"},{"name":"Micheline Franoise Marielle Goitschel","y":169,"x":64,"t":"FRA","custom":"Alpské lyžování"},{"name":"Nancy Catherine Greene (-Raine)","y":160,"x":62,"t":"CAN","custom":"Alpské lyžování"},{"name":"Christl Haas","y":177,"x":70,"t":"AUT","custom":"Alpské lyžování"},{"name":"Joan Lee Hannah (-Robinson)","y":162,"x":57,"t":"USA","custom":"Alpské lyžování"},{"name":"Georgina Melissa \"Gina\" Hathorn (-Sopwith)","y":169,"x":65,"t":"GBR","custom":"Alpské lyžování"},{"name":"Tania Elisabeth Heald (-Dereham)","y":155,"x":53,"t":"GBR","custom":"Alpské lyžování"},{"name":"Barbara-Maria \"Barbi\" Henneberger","y":168,"x":51,"t":"GER","custom":"Alpské lyžování"},{"name":"Nancy E. Holland (-Podorigzach)","y":156,"x":65,"t":"CAN","custom":"Alpské lyžování"},{"name":"Yevgeniya Nikolayevna Kabina-Sidorova","y":164,"x":65,"t":"URS","custom":"Alpské lyžování"},{"name":"Patrizia Medail Occioni Bonaffons","y":159,"x":52,"t":"ITA","custom":"Alpské lyžování"},{"name":"Linda Meyers (-Tikalsky)","y":164,"x":57,"t":"USA","custom":"Alpské lyžování"},{"name":"Heide \"Heidi\" Mittermaier (-Fischer)","y":159,"x":52,"t":"GER","custom":"Alpské lyžování"},{"name":"Heidi Obrecht","y":169,"x":66,"t":"SUI","custom":"Alpské lyžování"},{"name":"Theres Obrecht","y":165,"x":59,"t":"SUI","custom":"Alpské lyžování"},{"name":"Ccile Prince (-Doucerain)","y":170,"x":60,"t":"FRA","custom":"Alpské lyžování"},{"name":"Pia Riva","y":162,"x":58,"t":"ITA","custom":"Alpské lyžování"},{"name":"Jean Marlene Saubert","y":167,"x":68,"t":"USA","custom":"Alpské lyžování"},{"name":"Anna Inge Senoner","y":156,"x":57,"t":"ITA","custom":"Alpské lyžování"},{"name":"Galina Vladimirovna Sidorova (-Beker)","y":155,"x":55,"t":"URS","custom":"Alpské lyžování"},{"name":"Christine Terraillon (-Jauffret)","y":168,"x":58,"t":"FRA","custom":"Alpské lyžování"},{"name":"Margo Lee Walters (-McDonald)","y":157,"x":52,"t":"USA","custom":"Alpské lyžování"},{"name":"Starr Walton (-Hurley)","y":161,"x":57,"t":"USA","custom":"Alpské lyžování"}]},{"index":7,"showInLegend":true,"name":"Saně + Skeleton","data":[{"name":"Ursula Amstein","y":172,"x":58,"t":"SUI","custom":"Saně"},{"name":"Erika Auersdorfer","y":168,"x":60,"t":"ITA","custom":"Saně"},{"name":"Wilhelmine \"Minna\" Blml","y":170,"x":70,"t":"GER","custom":"Saně"},{"name":"Ortrun Enderlein (-Zphel)","y":163,"x":56,"t":"GER","custom":"Saně"},{"name":"Ilse Geisler (-Vorspach)","y":168,"x":60,"t":"GER","custom":"Saně"},{"name":"Barbara Gorgo-Flont","y":166,"x":53,"t":"POL","custom":"Saně"},{"name":"Oldka \"Olina\" Htlov-Tylov (-Nagenrauft)","y":171,"x":69,"t":"TCH","custom":"Saně"},{"name":"Dorothy Ann \"Dee\" Hirschland","y":164,"x":64,"t":"USA","custom":"Saně"},{"name":"Monika Lcker","y":162,"x":56,"t":"SUI","custom":"Saně"},{"name":"Helena Macher (-Ochmaska)","y":164,"x":61,"t":"POL","custom":"Saně"},{"name":"Elisabeth Nagele","y":160,"x":59,"t":"SUI","custom":"Saně"},{"name":"Hana Nesvadbov","y":162,"x":56,"t":"TCH","custom":"Saně"},{"name":"Irena Paweczyk (-Kowalska)","y":159,"x":68,"t":"POL","custom":"Saně"},{"name":"Erica Prugger","y":160,"x":48,"t":"ITA","custom":"Saně"},{"name":"Helene \"Leni\" Thurner (-Bullock)","y":168,"x":58,"t":"AUT","custom":"Saně"}]},{"index":8,"showInLegend":false,"name":"Akrobatické lyžování + Snowboarding","data":[]},{"index":9,"showInLegend":false,"name":"Curling","data":[]},{"index":10,"showInLegend":false,"name":"Alpinismus","data":[]}]}