{"legendLength":9,"data":[{"index":0,"showInLegend":false,"name":"Skoky na lyžích + Severská kombinace","visible":true,"data":[]},{"index":1,"showInLegend":true,"name":"Boby","visible":true,"data":[{"name":"Maya Bamert (-Regg)","y":182,"x":81,"t":"SUI","custom":"Boby"},{"name":"Ilse Maria Broeders","y":172,"x":68,"t":"NED","custom":"Boby"},{"name":"Jamie Cruickshank","y":177,"x":74,"t":"CAN","custom":"Boby"},{"name":"Jacqueline \"Jackie\" Davies (-Gunn)","y":162,"x":70,"t":"GBR","custom":"Boby"},{"name":"Susi-Lisa Erdmann (-Plankensteiner)","y":187,"x":80,"t":"GER","custom":"Boby"},{"name":"Martina Feusi","y":169,"x":65,"t":"SUI","custom":"Boby"},{"name":"Valerie S. Fleming","y":173,"x":77,"t":"USA","custom":"Boby"},{"name":"Vonetta Lashaw Flowers (Jeffery-)","y":167,"x":70,"t":"USA","custom":"Boby"},{"name":"Nicola Louise Gautier-Minichiello","y":167,"x":80,"t":"GBR","custom":"Boby"},{"name":"Suzanne Gavine-Hlady","y":168,"x":77,"t":"CAN","custom":"Boby"},{"name":"Jessica Gillarduzzi","y":170,"x":70,"t":"ITA","custom":"Boby"},{"name":"Sabina Hafner","y":168,"x":63,"t":"SUI","custom":"Boby"},{"name":"Nicole Herschmann","y":180,"x":71,"t":"GER","custom":"Boby"},{"name":"Manami Hino","y":160,"x":60,"t":"JPN","custom":"Boby"},{"name":"Cora Huber","y":174,"x":64,"t":"SUI","custom":"Boby"},{"name":"Jennifer Isacco","y":173,"x":64,"t":"ITA","custom":"Boby"},{"name":"Eline Jurg","y":177,"x":73,"t":"NED","custom":"Boby"},{"name":"Astrid Loch-Wilkinson-Raenovi","y":168,"x":70,"t":"AUS","custom":"Boby"},{"name":"Fabiana Mollica","y":175,"x":70,"t":"ITA","custom":"Boby"},{"name":"Heather Moyse","y":178,"x":72,"t":"CAN","custom":"Boby"},{"name":"Chisato Nagaoka","y":165,"x":70,"t":"JPN","custom":"Boby"},{"name":"Nadezhda Anatolyevna Orlova","y":165,"x":78,"t":"RUS","custom":"Boby"},{"name":"Jeannette Ingeborg Cornelia Pennings","y":176,"x":68,"t":"NED","custom":"Boby"},{"name":"Sandra Prokoff-Kiriasis","y":182,"x":80,"t":"GER","custom":"Boby"},{"name":"Jean Racine-Prahm","y":162,"x":61,"t":"USA","custom":"Boby"},{"name":"Kylie Reed","y":179,"x":63,"t":"AUS","custom":"Boby"},{"name":"Shauna L. Rohbock","y":173,"x":75,"t":"USA","custom":"Boby"},{"name":"Anja Schneiderheinze (-Stckel)","y":169,"x":79,"t":"GER","custom":"Boby"},{"name":"Viktoriya Ivanovna Tokovaya","y":175,"x":73,"t":"RUS","custom":"Boby"},{"name":"Helen Lesley Upperton","y":175,"x":73,"t":"CAN","custom":"Boby"},{"name":"Kitty van Haperen","y":172,"x":77,"t":"NED","custom":"Boby"},{"name":"Gerda Weissensteiner","y":166,"x":63,"t":"ITA","custom":"Boby"}]},{"index":2,"showInLegend":true,"name":"Krasobruslení","visible":true,"data":[{"name":"Marina Aganina","y":158,"x":51,"t":"UZB","custom":"Krasobruslení"},{"name":"Miki Ando","y":162,"x":50,"t":"JPN","custom":"Krasobruslení"},{"name":"Shizuka Arakawa","y":164,"x":50,"t":"JPN","custom":"Krasobruslení"},{"name":"Tanith Jessica Louise Belbin","y":167,"x":52,"t":"USA","custom":"Krasobruslení"},{"name":"Yuliya Bilohlazova","y":164,"x":51,"t":"UKR","custom":"Krasobruslení"},{"name":"Joanne Carter","y":159,"x":52,"t":"AUS","custom":"Krasobruslení"},{"name":"Galit Chait","y":153,"x":45,"t":"ISR","custom":"Krasobruslení"},{"name":"Alexandra Pauline \"Sasha\" Cohen","y":157,"x":43,"t":"USA","custom":"Krasobruslení"},{"name":"Isabelle Delobel","y":163,"x":50,"t":"FRA","custom":"Krasobruslení"},{"name":"Albena Petrova Denkova (-Stavisky)","y":165,"x":52,"t":"BUL","custom":"Krasobruslení"},{"name":"Oksana Aleksandrovna Domnina","y":173,"x":56,"t":"RUS","custom":"Krasobruslení"},{"name":"Margarita Drobiazko","y":170,"x":58,"t":"LTU","custom":"Krasobruslení"},{"name":"Jessica Dub","y":150,"x":52,"t":"CAN","custom":"Krasobruslení"},{"name":"Marie-France Dubreuil","y":162,"x":46,"t":"CAN","custom":"Krasobruslení"},{"name":"Federica Faiella","y":166,"x":55,"t":"ITA","custom":"Krasobruslení"},{"name":"Eva-Maria Fitze","y":159,"x":48,"t":"GER","custom":"Krasobruslení"},{"name":"Silvia Fontana (-Zimmerman)","y":158,"x":55,"t":"ITA","custom":"Krasobruslení"},{"name":"Kristin Fraser","y":168,"x":52,"t":"AZE","custom":"Krasobruslení"},{"name":"Barbara Fusar Poli","y":168,"x":51,"t":"ITA","custom":"Krasobruslení"},{"name":"Elene Gedevanishvili","y":160,"x":41,"t":"GEO","custom":"Krasobruslení"},{"name":"Anastasiya Gimazetdinova","y":180,"x":56,"t":"UZB","custom":"Krasobruslení"},{"name":"Jelena Glebova","y":165,"x":49,"t":"EST","custom":"Krasobruslení"},{"name":"Anastasia Grebenkina","y":168,"x":53,"t":"ARM","custom":"Krasobruslení"},{"name":"Melissa Gregory","y":165,"x":49,"t":"USA","custom":"Krasobruslení"},{"name":"Idora Hegel","y":167,"x":53,"t":"CRO","custom":"Krasobruslení"},{"name":"Marcy Hinzmann","y":155,"x":48,"t":"USA","custom":"Krasobruslení"},{"name":"Nra Hoffmann","y":171,"x":56,"t":"HUN","custom":"Krasobruslení"},{"name":"Yuliya Holovina","y":165,"x":50,"t":"UKR","custom":"Krasobruslení"},{"name":"Olena Eduardivna Hrushyna (-Honcharova-)","y":168,"x":52,"t":"UKR","custom":"Krasobruslení"},{"name":"Rena Inoue","y":150,"x":42,"t":"USA","custom":"Krasobruslení"},{"name":"Tuba Karademir","y":165,"x":63,"t":"TUR","custom":"Krasobruslení"},{"name":"Aleksandra Kauc","y":160,"x":60,"t":"POL","custom":"Krasobruslení"},{"name":"Sinead Houston Kerr","y":167,"x":54,"t":"GBR","custom":"Krasobruslení"},{"name":"Yana Vadimovna Khokhlova","y":155,"x":41,"t":"RUS","custom":"Krasobruslení"},{"name":"Kim Yong-Suk","y":150,"x":48,"t":"PRK","custom":"Krasobruslení"},{"name":"Kiira Linda Katriina Korpi","y":166,"x":58,"t":"FIN","custom":"Krasobruslení"},{"name":"Carolina Kostner","y":169,"x":60,"t":"ITA","custom":"Krasobruslení"},{"name":"Olena Anatolivna Liashenko","y":160,"x":48,"t":"UKR","custom":"Krasobruslení"},{"name":"Liu Yan","y":164,"x":52,"t":"CHN","custom":"Krasobruslení"},{"name":"Roxana Maria Luca","y":164,"x":55,"t":"ROU","custom":"Krasobruslení"},{"name":"Halyna Maniachenko-Yefremenko","y":162,"x":52,"t":"UKR","custom":"Krasobruslení"},{"name":"Fleur Maxwell","y":158,"x":48,"t":"LUX","custom":"Krasobruslení"},{"name":"Sarah Meier","y":164,"x":49,"t":"SUI","custom":"Krasobruslení"},{"name":"Kimberley Claire \"Kimmie\" Meissner","y":160,"x":45,"t":"USA","custom":"Krasobruslení"},{"name":"Tatyana Aleksandrovna Navka","y":170,"x":52,"t":"RUS","custom":"Krasobruslení"},{"name":"Yuliya Nikolayevna Obertas","y":152,"x":41,"t":"RUS","custom":"Krasobruslení"},{"name":"Pang Qing","y":160,"x":46,"t":"CHN","custom":"Krasobruslení"},{"name":"Viktria Pavuk","y":168,"x":53,"t":"HUN","custom":"Krasobruslení"},{"name":"Nathalie Pchalat","y":163,"x":50,"t":"FRA","custom":"Krasobruslení"},{"name":"Mariya Igorevna Petrova","y":152,"x":45,"t":"RUS","custom":"Krasobruslení"},{"name":"Phyo Yong-Myong","y":150,"x":38,"t":"PRK","custom":"Krasobruslení"},{"name":"Marylin Pla","y":153,"x":46,"t":"FRA","custom":"Krasobruslení"},{"name":"Susanna Kristina Pyki","y":159,"x":49,"t":"FIN","custom":"Krasobruslení"},{"name":"Diana Rennik","y":161,"x":48,"t":"EST","custom":"Krasobruslení"},{"name":"Joannie Rochette","y":160,"x":53,"t":"CAN","custom":"Krasobruslení"},{"name":"Aljona Sawtchenko","y":153,"x":48,"t":"GER","custom":"Krasobruslení"},{"name":"Jlia Sebestyn","y":164,"x":66,"t":"HUN","custom":"Krasobruslení"},{"name":"Shen Xue","y":160,"x":45,"t":"CHN","custom":"Krasobruslení"},{"name":"Jamie Silverstein","y":160,"x":46,"t":"USA","custom":"Krasobruslení"},{"name":"Irina Eduardovna Slutskaya","y":160,"x":49,"t":"RUS","custom":"Krasobruslení"},{"name":"Yelena Sergeyevna Sokolova","y":162,"x":51,"t":"RUS","custom":"Krasobruslení"},{"name":"Rumyana Spasova","y":147,"x":46,"t":"BUL","custom":"Krasobruslení"},{"name":"Fumie Suguri","y":157,"x":45,"t":"JPN","custom":"Krasobruslení"},{"name":"Tatyana Ivanovna Totmyanina","y":160,"x":44,"t":"RUS","custom":"Krasobruslení"},{"name":"Tetiana Andrivna Volosozhar","y":159,"x":44,"t":"UKR","custom":"Krasobruslení"},{"name":"Nozomi Watanabe","y":158,"x":48,"t":"JPN","custom":"Krasobruslení"},{"name":"Dorota Magdalena Zagrska-Siudek","y":155,"x":44,"t":"POL","custom":"Krasobruslení"},{"name":"Alexandra Zaretski","y":160,"x":55,"t":"ISR","custom":"Krasobruslení"},{"name":"Zhang Dan","y":167,"x":48,"t":"CHN","custom":"Krasobruslení"}]},{"index":3,"showInLegend":true,"name":"Rychlobruslení + Short track","visible":false,"data":[{"name":"Yekaterina Konstantinovna Abramova","y":167,"x":65,"t":"RUS","custom":"Rychlobruslení"},{"name":"Daniela Anschtz-Thoms","y":165,"x":60,"t":"GER","custom":"Rychlobruslení"},{"name":"Varvara Borisovna Barysheva","y":168,"x":62,"t":"RUS","custom":"Rychlobruslení"},{"name":"Allison Baver","y":160,"x":57,"t":"USA","custom":"Short track"},{"name":"Annette Bjelkevik","y":168,"x":63,"t":"NOR","custom":"Rychlobruslení"},{"name":"Hedvig Bjelkevik","y":162,"x":57,"t":"NOR","custom":"Rychlobruslení"},{"name":"Tatyana Aleksandrovna Borodulina","y":160,"x":52,"t":"RUS","custom":"Short track"},{"name":"Stphanie Bouvier","y":163,"x":58,"t":"FRA","custom":"Short track"},{"name":"Svetlana Sergeyevna Boyarkina-Zhurova","y":176,"x":64,"t":"RUS","custom":"Rychlobruslení"},{"name":"Byeon Cheon-Sa","y":167,"x":58,"t":"KOR","custom":"Short track"},{"name":"Marta Capurso","y":155,"x":55,"t":"ITA","custom":"Short track"},{"name":"Cheng Xiaolei","y":167,"x":58,"t":"CHN","custom":"Short track"},{"name":"Choi Eun-Gyeong","y":165,"x":62,"t":"KOR","custom":"Short track"},{"name":"Choi Min-Kyung","y":162,"x":60,"t":"FRA","custom":"Short track"},{"name":"Choi Seung-Yong","y":160,"x":58,"t":"KOR","custom":"Rychlobruslení"},{"name":"Margaret Yates \"Maggie\" Crowley","y":162,"x":61,"t":"USA","custom":"Rychlobruslení"},{"name":"Rzsa Darzs","y":180,"x":65,"t":"HUN","custom":"Short track"},{"name":"Barbara de Loor","y":180,"x":70,"t":"NED","custom":"Rychlobruslení"},{"name":"Kimberly Derrick","y":165,"x":56,"t":"USA","custom":"Short track"},{"name":"Arianna Fontana","y":164,"x":63,"t":"ITA","custom":"Short track"},{"name":"Anna Christine \"Anni\" Friesinger-Postma","y":169,"x":64,"t":"GER","custom":"Rychlobruslení"},{"name":"Fu Tianyu","y":161,"x":55,"t":"CHN","custom":"Short track"},{"name":"Gang Yun-Mi","y":155,"x":46,"t":"KOR","custom":"Short track"},{"name":"Maria Cruz Garcia","y":154,"x":62,"t":"USA","custom":"Short track"},{"name":"Annette Albertine Gerritsen","y":171,"x":61,"t":"NED","custom":"Rychlobruslení"},{"name":"Myrtille Gollin","y":168,"x":57,"t":"FRA","custom":"Short track"},{"name":"Tina Grassow","y":160,"x":53,"t":"GER","custom":"Short track"},{"name":"Renate Titzia Groenewold","y":180,"x":74,"t":"NED","custom":"Rychlobruslení"},{"name":"Kristina Nicole Groves","y":175,"x":66,"t":"CAN","custom":"Rychlobruslení"},{"name":"Caroline Hallisey (-Kepka)","y":162,"x":60,"t":"USA","custom":"Short track"},{"name":"Han Yue Shuang","y":175,"x":54,"t":"HKG","custom":"Short track"},{"name":"Maren Haugli (-Tufto)","y":173,"x":62,"t":"NOR","custom":"Rychlobruslení"},{"name":"Judith Hesse (-Dannhauer)","y":158,"x":50,"t":"GER","custom":"Rychlobruslení"},{"name":"Kristine L. Holzer","y":173,"x":70,"t":"USA","custom":"Rychlobruslení"},{"name":"Clara Hughes","y":175,"x":72,"t":"CAN","custom":"Rychlobruslení"},{"name":"Erika Huszr","y":165,"x":59,"t":"HUN","custom":"Short track"},{"name":"Eriko Ishino","y":168,"x":63,"t":"JPN","custom":"Rychlobruslení"},{"name":"Jeon Da-Hye","y":170,"x":63,"t":"KOR","custom":"Short track"},{"name":"Ji Jia","y":168,"x":62,"t":"CHN","custom":"Rychlobruslení"},{"name":"Jin Seon-Yu","y":164,"x":56,"t":"KOR","custom":"Short track"},{"name":"Yuka Kamino","y":163,"x":54,"t":"JPN","custom":"Short track"},{"name":"Hyo-Jung Kim","y":165,"x":55,"t":"USA","custom":"Short track"},{"name":"Kim Yu-Rim","y":166,"x":57,"t":"KOR","custom":"Rychlobruslení"},{"name":"Cynthia Nicole \"Cindy\" Klassen","y":173,"x":71,"t":"CAN","custom":"Rychlobruslení"},{"name":"Meiskelina Catharina Anna \"Carien\" Kleibeuker","y":172,"x":59,"t":"NED","custom":"Rychlobruslení"},{"name":"Aika Klein","y":169,"x":63,"t":"GER","custom":"Short track"},{"name":"Moniek Frida Maria Kleinsman","y":164,"x":59,"t":"NED","custom":"Rychlobruslení"},{"name":"Alanna Kraus (-Handley)","y":165,"x":60,"t":"CAN","custom":"Short track"},{"name":"Evita Krievne","y":167,"x":58,"t":"LAT","custom":"Short track"},{"name":"Katalin Kristo","y":160,"x":54,"t":"ROU","custom":"Short track"},{"name":"Yvonne Kunze","y":155,"x":49,"t":"GER","custom":"Short track"},{"name":"Maria Teresa Sullivan Lamb","y":168,"x":59,"t":"USA","custom":"Rychlobruslení"},{"name":"Anouk Leblanc-Boucher","y":170,"x":62,"t":"CAN","custom":"Short track"},{"name":"Cline Lecompre","y":164,"x":54,"t":"FRA","custom":"Short track"},{"name":"Lee Bo-Ra","y":167,"x":55,"t":"KOR","custom":"Rychlobruslení"},{"name":"Lee Ju-Yeon","y":163,"x":52,"t":"KOR","custom":"Rychlobruslení"},{"name":"Lee Sang-Hwa","y":165,"x":62,"t":"KOR","custom":"Rychlobruslení"},{"name":"Galina Vladimirovna Likhachova","y":168,"x":65,"t":"RUS","custom":"Rychlobruslení"},{"name":"Sarah Diane T. Lindsay","y":172,"x":60,"t":"GBR","custom":"Short track"},{"name":"Yekaterina Aleksandrovna Lobysheva","y":178,"x":69,"t":"RUS","custom":"Rychlobruslení"},{"name":"Adelia Marra","y":164,"x":61,"t":"ITA","custom":"Rychlobruslení"},{"name":"Liesbeth Eveline Mau-Asam","y":172,"x":59,"t":"NED","custom":"Short track"},{"name":"Krisy Myers","y":174,"x":69,"t":"CAN","custom":"Rychlobruslení"},{"name":"Yuliya Aleksandrovna Nemaya (-Liteykina)","y":166,"x":65,"t":"RUS","custom":"Rychlobruslení"},{"name":"Nami Nemoto","y":162,"x":58,"t":"JPN","custom":"Rychlobruslení"},{"name":"Christine Margaret Nesbitt","y":171,"x":68,"t":"CAN","custom":"Rychlobruslení"},{"name":"No Seon-Yeong","y":172,"x":66,"t":"KOR","custom":"Rychlobruslení"},{"name":"Kateřina Novotná","y":161,"x":57,"t":"CZE","custom":"Short track"},{"name":"Elizabeth Kristine \"Elli\" Ochowicz","y":160,"x":61,"t":"USA","custom":"Rychlobruslení"},{"name":"Tomomi Okazaki (Yasutake-)","y":164,"x":57,"t":"JPN","custom":"Rychlobruslení"},{"name":"Daniela Oltean","y":164,"x":60,"t":"ROU","custom":"Rychlobruslení"},{"name":"Lucille Opitz (-Weber)","y":169,"x":63,"t":"GER","custom":"Rychlobruslení"},{"name":"Sayuri Osuga","y":163,"x":58,"t":"JPN","custom":"Rychlobruslení"},{"name":"Hiromi Otsu","y":165,"x":59,"t":"JPN","custom":"Rychlobruslení"},{"name":"Amanda Overland","y":165,"x":57,"t":"CAN","custom":"Short track"},{"name":"Mika Ozawa","y":160,"x":50,"t":"JPN","custom":"Short track"},{"name":"Yuliya Sergeyevna Pavlovich-Yelsakova","y":161,"x":52,"t":"BLR","custom":"Short track"},{"name":"Claudia Pechstein","y":166,"x":61,"t":"GER","custom":"Rychlobruslení"},{"name":"Christin Priebst","y":169,"x":57,"t":"GER","custom":"Short track"},{"name":"Evgeniya Nikolova Radanova","y":166,"x":65,"t":"BUL","custom":"Short track"},{"name":"Svetlana Nikolayevna Radkevich","y":166,"x":58,"t":"BLR","custom":"Rychlobruslení"},{"name":"Catherine Raney Norman","y":170,"x":66,"t":"USA","custom":"Rychlobruslení"},{"name":"Shannon Colleen Rempel","y":173,"x":70,"t":"CAN","custom":"Rychlobruslení"},{"name":"Ren Hui","y":180,"x":77,"t":"CHN","custom":"Rychlobruslení"},{"name":"Ri Hyang-Mi","y":159,"x":59,"t":"PRK","custom":"Short track"},{"name":"Kalyna Roberge","y":160,"x":49,"t":"CAN","custom":"Short track"},{"name":"Jennifer Jill Rodriguez","y":162,"x":58,"t":"USA","custom":"Rychlobruslení"},{"name":"Anna Natalia Rokita","y":173,"x":63,"t":"AUT","custom":"Rychlobruslení"},{"name":"Emily Rosemond","y":168,"x":63,"t":"AUS","custom":"Short track"},{"name":"Susanne Rudolph","y":168,"x":56,"t":"GER","custom":"Short track"},{"name":"Nataliya Rybakova","y":178,"x":70,"t":"KAZ","custom":"Rychlobruslení"},{"name":"Martina Sáblíková","y":171,"x":53,"t":"CZE","custom":"Rychlobruslení"},{"name":"Amy Elizabeth Sannes","y":165,"x":61,"t":"USA","custom":"Rychlobruslení"},{"name":"Eriko Seo","y":159,"x":54,"t":"JPN","custom":"Rychlobruslení"},{"name":"Chiara Simionato","y":167,"x":63,"t":"ITA","custom":"Rychlobruslení"},{"name":"Kerry Simpson (-Dankers)","y":171,"x":73,"t":"CAN","custom":"Rychlobruslení"},{"name":"Grietje \"Gretha\" Smit","y":167,"x":60,"t":"NED","custom":"Rychlobruslení"},{"name":"Maki Tabata","y":162,"x":55,"t":"JPN","custom":"Rychlobruslení"},{"name":"Chikage Tanaka","y":157,"x":46,"t":"JPN","custom":"Short track"},{"name":"Ikue Teshigawara","y":156,"x":49,"t":"JPN","custom":"Short track"},{"name":"Maria Aaltje \"Marianne\" Timmer","y":174,"x":63,"t":"NED","custom":"Rychlobruslení"},{"name":"Aki Tonoike","y":170,"x":67,"t":"JPN","custom":"Rychlobruslení"},{"name":"Sanne Martha van der Star","y":171,"x":68,"t":"NED","custom":"Rychlobruslení"},{"name":"Paulien Ilse Maria van Deutekom","y":171,"x":72,"t":"NED","custom":"Rychlobruslení"},{"name":"Tania Vicent","y":168,"x":59,"t":"CAN","custom":"Short track"},{"name":"Sabine Vlker","y":162,"x":58,"t":"GER","custom":"Rychlobruslení"},{"name":"Svetlana Yuryevna Vysokova","y":170,"x":67,"t":"RUS","custom":"Rychlobruslení"},{"name":"Wang Beixing","y":174,"x":66,"t":"CHN","custom":"Rychlobruslení"},{"name":"Wang Fei","y":170,"x":66,"t":"CHN","custom":"Rychlobruslení"},{"name":"Wang Manli","y":167,"x":67,"t":"CHN","custom":"Rychlobruslení"},{"name":"Wang Meng","y":167,"x":60,"t":"CHN","custom":"Short track"},{"name":"Yukari Watanabe","y":161,"x":57,"t":"JPN","custom":"Rychlobruslení"},{"name":"Kimberly \"Kim\" Weger","y":161,"x":57,"t":"CAN","custom":"Rychlobruslení"},{"name":"Joanna Frances \"Jo\" Williams (-Eley)","y":171,"x":64,"t":"GBR","custom":"Short track"},{"name":"Christine Diane \"Chris\" Witty","y":167,"x":66,"t":"USA","custom":"Rychlobruslení"},{"name":"Katarzyna Wjcicka-Bachleda-Curu (-Trzebunia)","y":170,"x":62,"t":"POL","custom":"Rychlobruslení"},{"name":"Jenny Wolf (-Lotze)","y":172,"x":75,"t":"GER","custom":"Rychlobruslení"},{"name":"Irene Karlijn \"Ireen\" Wst","y":168,"x":65,"t":"NED","custom":"Rychlobruslení"},{"name":"Xing Aihua","y":168,"x":65,"t":"CHN","custom":"Rychlobruslení"},{"name":"Valentina Vladimirovna Yakshina","y":168,"x":60,"t":"RUS","custom":"Rychlobruslení"},{"name":"Nobuko Yamada","y":160,"x":48,"t":"JPN","custom":"Short track"},{"name":"Yang Yang","y":166,"x":58,"t":"CHN","custom":"Short track"},{"name":"Sayuri Yoshii","y":166,"x":60,"t":"JPN","custom":"Rychlobruslení"},{"name":"Yun Jong-Suk","y":165,"x":62,"t":"PRK","custom":"Short track"},{"name":"Zhang Shuang","y":172,"x":70,"t":"CHN","custom":"Rychlobruslení"},{"name":"Zhang Xiaolei","y":168,"x":63,"t":"CHN","custom":"Rychlobruslení"},{"name":"Katia Zini","y":164,"x":57,"t":"ITA","custom":"Short track"},{"name":"Mara Zini","y":169,"x":53,"t":"ITA","custom":"Short track"},{"name":"Pamela Zoellner (Fischer-)","y":177,"x":69,"t":"GER","custom":"Rychlobruslení"}]},{"index":4,"showInLegend":true,"name":"Běh na lyžích + Biatlon","visible":false,"data":[{"name":"Albina Khamitovna Akhatova","y":160,"x":55,"t":"RUS","custom":"Biatlon"},{"name":"Martine Albert","y":155,"x":47,"t":"CAN","custom":"Biatlon"},{"name":"Amanda Ammar","y":157,"x":54,"t":"CAN","custom":"Běh na lyžích"},{"name":"Lyudmila Arkadyevna Ananko","y":163,"x":55,"t":"BLR","custom":"Biatlon"},{"name":"Lina Marie Andersson","y":158,"x":58,"t":"SWE","custom":"Běh na lyžích"},{"name":"Gunn Margit Aas Andreassen","y":177,"x":60,"t":"NOR","custom":"Biatlon"},{"name":"Katrin Apel","y":172,"x":62,"t":"GER","custom":"Biatlon"},{"name":"Laia Aubert Torrents","y":165,"x":57,"t":"ESP","custom":"Běh na lyžích"},{"name":"Kelime Aydn-etinkaya","y":160,"x":54,"t":"TUR","custom":"Běh na lyžích"},{"name":"Sandrine Bailly","y":172,"x":58,"t":"FRA","custom":"Biatlon"},{"name":"Helena Erbenová (Balatková)","y":160,"x":50,"t":"CZE","custom":"Běh na lyžích"},{"name":"Nataliya Ivanovna Baranova (Masolkina-)","y":172,"x":65,"t":"RUS","custom":"Běh na lyžích"},{"name":"Lanny L. Barnes","y":163,"x":50,"t":"USA","custom":"Biatlon"},{"name":"Tracy Barnes","y":157,"x":48,"t":"USA","custom":"Biatlon"},{"name":"Viola Bauer","y":167,"x":61,"t":"GER","custom":"Běh na lyžích"},{"name":"Florence  Andre Isabelle Baverel-Robert","y":167,"x":60,"t":"FRA","custom":"Biatlon"},{"name":"Sylvie Becaert","y":166,"x":54,"t":"FRA","custom":"Biatlon"},{"name":"Maja Benedii","y":172,"x":60,"t":"SLO","custom":"Běh na lyžích"},{"name":"Tora Berger (-Tveldal)","y":166,"x":56,"t":"NOR","custom":"Biatlon"},{"name":"Marit Bjrgen","y":168,"x":64,"t":"NOR","custom":"Běh na lyžích"},{"name":"Anna Ivanovna Bogaly-Titovets","y":167,"x":58,"t":"RUS","custom":"Biatlon"},{"name":"Stefanie Bhler","y":170,"x":54,"t":"GER","custom":"Běh na lyžích"},{"name":"Seraina Boner","y":168,"x":55,"t":"SUI","custom":"Běh na lyžích"},{"name":"Esther Bottomley","y":167,"x":58,"t":"AUS","custom":"Běh na lyžích"},{"name":"lodie Bourgeois-Pin","y":163,"x":55,"t":"FRA","custom":"Běh na lyžích"},{"name":"Tadeja Brankovi (-Likozar)","y":163,"x":65,"t":"SLO","custom":"Biatlon"},{"name":"Andela Brice (Mosina-)","y":161,"x":50,"t":"LAT","custom":"Biatlon"},{"name":"Clare-Louise Brumley","y":184,"x":68,"t":"AUS","custom":"Běh na lyžích"},{"name":"Yelena Nikolayevna Burukhina","y":164,"x":57,"t":"RUS","custom":"Běh na lyžích"},{"name":"Yuliya Anatolyevna Chepalova","y":164,"x":54,"t":"RUS","custom":"Běh na lyžích"},{"name":"Valentina Ciurina","y":174,"x":68,"t":"MDA","custom":"Biatlon"},{"name":"Antonella Confortola-Wyatt","y":170,"x":51,"t":"ITA","custom":"Běh na lyžích"},{"name":"Chandra Crawford","y":175,"x":68,"t":"CAN","custom":"Běh na lyžích"},{"name":"Ekaterina Stefanova Dafovska (-Prodanova)","y":163,"x":54,"t":"BUL","custom":"Biatlon"},{"name":"Anna Viktoria Dahlberg-Olsson","y":165,"x":60,"t":"SWE","custom":"Běh na lyžích"},{"name":"Ursula \"Uschi\" Disl","y":163,"x":57,"t":"GER","custom":"Biatlon"},{"name":"Rebecca Ann Dussault (Quinn-)","y":165,"x":55,"t":"USA","custom":"Běh na lyžích"},{"name":"Elin Maria Ek","y":176,"x":69,"t":"SWE","custom":"Běh na lyžích"},{"name":"Erdene-Ochiryn Ochirsren","y":165,"x":61,"t":"MGL","custom":"Běh na lyžích"},{"name":"Barbara Ertl","y":166,"x":55,"t":"ITA","custom":"Biatlon"},{"name":"Vesna Fabjan","y":170,"x":62,"t":"SLO","custom":"Běh na lyžích"},{"name":"Lenka Faltusová","y":166,"x":61,"t":"CZE","custom":"Biatlon"},{"name":"Nicole Fessel","y":170,"x":55,"t":"GER","custom":"Běh na lyžích"},{"name":"Pavlina Ivanova Filipova","y":158,"x":54,"t":"BUL","custom":"Biatlon"},{"name":"Arianna Fernanda Follis","y":162,"x":55,"t":"ITA","custom":"Běh na lyžích"},{"name":"Emma Jane E. Fowler","y":172,"x":60,"t":"GBR","custom":"Biatlon"},{"name":"Nobuko Fukuda","y":164,"x":54,"t":"JPN","custom":"Běh na lyžích"},{"name":"Katarna Garajov","y":160,"x":54,"t":"SVK","custom":"Běh na lyžích"},{"name":"Magda Genuin","y":173,"x":62,"t":"ITA","custom":"Běh na lyžích"},{"name":"Jana \"Janka\" Gerekov","y":170,"x":64,"t":"SVK","custom":"Biatlon"},{"name":"Ella Gjmle (-Berg)","y":172,"x":61,"t":"NOR","custom":"Běh na lyžích"},{"name":"Martina Glagow-Beck","y":158,"x":48,"t":"GER","custom":"Biatlon"},{"name":"Elena Gorohova","y":168,"x":54,"t":"MDA","custom":"Běh na lyžích"},{"name":"Elena Gorohova","y":168,"x":54,"t":"MDA","custom":"Biatlon"},{"name":"Zsfia Gottschall","y":167,"x":55,"t":"HUN","custom":"Biatlon"},{"name":"Teja Gregorin","y":171,"x":56,"t":"SLO","custom":"Biatlon"},{"name":"Dijana Grudiek-Ravnikar","y":168,"x":53,"t":"SLO","custom":"Biatlon"},{"name":"Magdalena Grzywa","y":166,"x":51,"t":"POL","custom":"Biatlon"},{"name":"Nataliya Vladimirovna Guseva (-Sorokina)","y":165,"x":60,"t":"RUS","custom":"Biatlon"},{"name":"Magdalena Gwizdo","y":178,"x":66,"t":"POL","custom":"Biatlon"},{"name":"Leila Gyenesei","y":180,"x":61,"t":"HUN","custom":"Běh na lyžích"},{"name":"Monika Gyorgy","y":162,"x":50,"t":"ROU","custom":"Běh na lyžích"},{"name":"Katja Haller","y":162,"x":61,"t":"ITA","custom":"Biatlon"},{"name":"Andrea Henkel (-Burke)","y":159,"x":49,"t":"GER","custom":"Biatlon"},{"name":"Manuela Henkel","y":168,"x":56,"t":"GER","custom":"Běh na lyžích"},{"name":"Hou Yuxia","y":169,"x":58,"t":"CHN","custom":"Biatlon"},{"name":"Kateryna Vasylivna Hryhorenko","y":166,"x":65,"t":"UKR","custom":"Běh na lyžích"},{"name":"Huo Li","y":159,"x":49,"t":"CHN","custom":"Běh na lyžích"},{"name":"Nataliya Isachenko","y":166,"x":58,"t":"KAZ","custom":"Běh na lyžích"},{"name":"Vernica Isbej Morales","y":162,"x":52,"t":"CHI","custom":"Biatlon"},{"name":"Masako Ishida","y":161,"x":56,"t":"JPN","custom":"Běh na lyžích"},{"name":"Svetlana Irekovna Ishmuratova","y":165,"x":57,"t":"RUS","custom":"Biatlon"},{"name":"Yekaterina Gennadyevna Ivanova (-Vinogradova)","y":174,"x":63,"t":"BLR","custom":"Biatlon"},{"name":"Ivana \"Iva\" Janekov","y":158,"x":54,"t":"CZE","custom":"Běh na lyžích"},{"name":"Martina Jaicov-Schwarzbacherov-Halinrov","y":164,"x":52,"t":"SVK","custom":"Biatlon"},{"name":"Jia Yuping","y":170,"x":62,"t":"CHN","custom":"Běh na lyžích"},{"name":"Jiang Chunli","y":162,"x":53,"t":"CHN","custom":"Běh na lyžích"},{"name":"Britta Johanna Helena Johansson-Norgren","y":169,"x":67,"t":"SWE","custom":"Běh na lyžích"},{"name":"Nina Kadeva-Klenovska","y":174,"x":61,"t":"BUL","custom":"Biatlon"},{"name":"Sandra Keith","y":170,"x":55,"t":"CAN","custom":"Biatlon"},{"name":"Maja Kezele","y":169,"x":60,"t":"CRO","custom":"Běh na lyžích"},{"name":"Oksana Yurivna Khvostenko","y":167,"x":60,"t":"UKR","custom":"Biatlon"},{"name":"Zina Kocher","y":170,"x":60,"t":"CAN","custom":"Biatlon"},{"name":"Yelena Vladimirovna Kolomina","y":158,"x":50,"t":"KAZ","custom":"Běh na lyžích"},{"name":"Kong Yingchao","y":165,"x":55,"t":"CHN","custom":"Biatlon"},{"name":"Sarah Konrad","y":160,"x":61,"t":"USA","custom":"Biatlon"},{"name":"Sarah Konrad","y":160,"x":61,"t":"USA","custom":"Běh na lyžích"},{"name":"Lyudmila Petrovna Korolik (-Shablovskaya)","y":166,"x":54,"t":"BLR","custom":"Běh na lyžích"},{"name":"Justyna Kowalczyk","y":173,"x":59,"t":"POL","custom":"Běh na lyžích"},{"name":"Gro Marit Istad Kristiansen","y":175,"x":65,"t":"NOR","custom":"Biatlon"},{"name":"Gerda Krmia","y":166,"x":56,"t":"LAT","custom":"Biatlon"},{"name":"Virpi Katriina Kuitunen (-Sarasvuo)","y":174,"x":65,"t":"FIN","custom":"Běh na lyžích"},{"name":"Claudia Knzel-Nystad","y":168,"x":58,"t":"GER","custom":"Běh na lyžích"},{"name":"Larisa Nikolayevna Kurkina","y":169,"x":55,"t":"RUS","custom":"Běh na lyžích"},{"name":"Branka Kuzeljevi","y":168,"x":55,"t":"SCG","custom":"Běh na lyžích"},{"name":"Abigail Jean \"Abby\" Larson","y":170,"x":50,"t":"USA","custom":"Běh na lyžích"},{"name":"Riitta-Liisa Lassila-Roponen","y":161,"x":54,"t":"FIN","custom":"Běh na lyžích"},{"name":"Anna Petrovna Lebedeva","y":178,"x":70,"t":"KAZ","custom":"Biatlon"},{"name":"Lee Chae-Won","y":154,"x":49,"t":"KOR","custom":"Běh na lyžích"},{"name":"Nina Petrivna Lemesh","y":161,"x":54,"t":"UKR","custom":"Biatlon"},{"name":"Natascia Leonardi Cortesi","y":163,"x":51,"t":"SUI","custom":"Běh na lyžích"},{"name":"Natalia Levcencova","y":160,"x":52,"t":"MDA","custom":"Biatlon"},{"name":"Li Hongxue","y":160,"x":52,"t":"CHN","custom":"Běh na lyžích"},{"name":"Madara Lduma","y":167,"x":60,"t":"LAT","custom":"Biatlon"},{"name":"Liu Liming","y":166,"x":62,"t":"CHN","custom":"Běh na lyžích"},{"name":"Liu Xianying","y":160,"x":52,"t":"CHN","custom":"Biatlon"},{"name":"Liu Yuanyuan","y":162,"x":53,"t":"CHN","custom":"Běh na lyžích"},{"name":"Viktoriya Viktorovna Lopatina","y":160,"x":61,"t":"BLR","custom":"Běh na lyžích"},{"name":"Kateřina Holubcová (Losmanová)","y":168,"x":55,"t":"CZE","custom":"Biatlon"},{"name":"Petra Majdi","y":176,"x":65,"t":"SLO","custom":"Běh na lyžích"},{"name":"Maryna Oleksandrivna Malets-Lisohor","y":175,"x":64,"t":"UKR","custom":"Běh na lyžích"},{"name":"Andreja Mali","y":160,"x":54,"t":"SLO","custom":"Biatlon"},{"name":"Man Dandan","y":165,"x":56,"t":"CHN","custom":"Běh na lyžích"},{"name":"Tatjana Mannima","y":158,"x":53,"t":"EST","custom":"Běh na lyžích"},{"name":"Nataliya Konstantinovna Matveyeva","y":168,"x":56,"t":"RUS","custom":"Běh na lyžích"},{"name":"Yevgeniya Vladimirovna Medvedeva (Arbuzova-)","y":158,"x":56,"t":"RUS","custom":"Běh na lyžích"},{"name":"Kanae Meguro (Suzuki-)","y":157,"x":51,"t":"JPN","custom":"Biatlon"},{"name":"Soa Mihokov","y":165,"x":50,"t":"SVK","custom":"Biatlon"},{"name":"Seraina Mischol","y":167,"x":60,"t":"SUI","custom":"Běh na lyžích"},{"name":"Barbara Moriggl","y":160,"x":53,"t":"ITA","custom":"Běh na lyžích"},{"name":"Jaqueline Mouro","y":170,"x":55,"t":"BRA","custom":"Běh na lyžích"},{"name":"Anna Murnov","y":165,"x":52,"t":"SVK","custom":"Biatlon"},{"name":"Madoka Natsumi","y":170,"x":59,"t":"JPN","custom":"Běh na lyžích"},{"name":"Olga Viktorovna Nazarova","y":164,"x":53,"t":"BLR","custom":"Biatlon"},{"name":"Kateřina Neumannová","y":175,"x":67,"t":"CZE","custom":"Běh na lyžích"},{"name":"Irina Kostadinova Nikulchina","y":172,"x":55,"t":"BUL","custom":"Biatlon"},{"name":"Irena Česneková (Novotná)","y":158,"x":52,"t":"CZE","custom":"Biatlon"},{"name":"Magdalena Nykiel","y":166,"x":58,"t":"POL","custom":"Biatlon"},{"name":"Frida Emelie hrstig","y":170,"x":62,"t":"SWE","custom":"Běh na lyžích"},{"name":"Anna-Carin Helena Cecilia Olofsson-Zidek","y":159,"x":55,"t":"SWE","custom":"Biatlon"},{"name":"Laura Orgue Vila","y":173,"x":55,"t":"ESP","custom":"Běh na lyžích"},{"name":"Tomomi Otaka","y":162,"x":56,"t":"JPN","custom":"Biatlon"},{"name":"Cristina Paluselli","y":165,"x":54,"t":"ITA","custom":"Běh na lyžích"},{"name":"Marie-Pierre Parent","y":165,"x":57,"t":"CAN","custom":"Biatlon"},{"name":"Gabriella Paruzzi","y":173,"x":62,"t":"ITA","custom":"Běh na lyžích"},{"name":"Marcela Pavkovekov","y":164,"x":55,"t":"SVK","custom":"Biatlon"},{"name":"Krystyna Stanisawa Paka (-Guzik)","y":165,"x":59,"t":"POL","custom":"Biatlon"},{"name":"Hilde Gjermundshaug Pedersen","y":167,"x":63,"t":"NOR","custom":"Běh na lyžích"},{"name":"Delphyne Peretto","y":170,"x":56,"t":"FRA","custom":"Biatlon"},{"name":"Aurlie Perrillat-Collomb Storti","y":178,"x":58,"t":"FRA","custom":"Běh na lyžích"},{"name":"Olena Yurivna Petrova","y":162,"x":54,"t":"UKR","custom":"Biatlon"},{"name":"Karine Laurent Philippot (-Laurent)","y":167,"x":56,"t":"FRA","custom":"Běh na lyžích"},{"name":"Anna Elina Pienimki-Hietamki","y":171,"x":62,"t":"FIN","custom":"Běh na lyžích"},{"name":"Dana Elena Plotogea-Cojocea","y":173,"x":63,"t":"ROU","custom":"Biatlon"},{"name":"Katarzyna Ponikwia","y":166,"x":55,"t":"POL","custom":"Biatlon"},{"name":"Michela Ponza","y":164,"x":52,"t":"ITA","custom":"Biatlon"},{"name":"Radka Kostadinova Popova","y":167,"x":62,"t":"BUL","custom":"Biatlon"},{"name":"Piret Pormeister","y":179,"x":65,"t":"EST","custom":"Běh na lyžích"},{"name":"Alena Prochzkov","y":171,"x":55,"t":"SVK","custom":"Běh na lyžích"},{"name":"Sabina Mihaela Purdea","y":163,"x":52,"t":"ROU","custom":"Biatlon"},{"name":"Olga Valeryevna Pylyova-Medvedtseva (Zamorozova-)","y":163,"x":55,"t":"RUS","custom":"Biatlon"},{"name":"Kamila Rajdlová","y":172,"x":61,"t":"CZE","custom":"Běh na lyžích"},{"name":"Kikkan Lewis Randall (-Ellis)","y":165,"x":60,"t":"USA","custom":"Běh na lyžích"},{"name":"Diana Rasimoviit","y":164,"x":52,"t":"LTU","custom":"Biatlon"},{"name":"Sara Renner","y":168,"x":63,"t":"CAN","custom":"Běh na lyžích"},{"name":"Magda Rezlerová","y":163,"x":55,"t":"CZE","custom":"Biatlon"},{"name":"Laurence Rochat","y":176,"x":61,"t":"SUI","custom":"Běh na lyžích"},{"name":"Olga Vladimirovna Rocheva (Moskalenko-)","y":178,"x":65,"t":"RUS","custom":"Běh na lyžích"},{"name":"Yekaterina Ivanovna Rudakova-Bulavka","y":164,"x":56,"t":"BLR","custom":"Běh na lyžích"},{"name":"Alexandra Rusu-Stoian","y":167,"x":53,"t":"ROU","custom":"Biatlon"},{"name":"Aino-Kaisa Saarinen","y":166,"x":58,"t":"FIN","custom":"Běh na lyžích"},{"name":"Evi Sachenbacher-Stehle","y":162,"x":52,"t":"GER","custom":"Běh na lyžích"},{"name":"Yelena Sergeyevna Sannikova","y":174,"x":60,"t":"BLR","custom":"Běh na lyžích"},{"name":"Nathalie Santer (-Bjrndalen)","y":172,"x":55,"t":"ITA","custom":"Biatlon"},{"name":"Saskia Santer","y":173,"x":60,"t":"ITA","custom":"Biatlon"},{"name":"Eveli Saue","y":163,"x":53,"t":"EST","custom":"Biatlon"},{"name":"Linda Savaka","y":171,"x":70,"t":"LAT","custom":"Biatlon"},{"name":"Rebecca \"Beckie\" Scott (-Wadsworth)","y":171,"x":64,"t":"CAN","custom":"Běh na lyžích"},{"name":"Valentyna Oleksandrivna \"Valj\" Semerenko","y":161,"x":54,"t":"UKR","custom":"Biatlon"},{"name":"Valentyna Yevhenivna Shevchenko","y":165,"x":51,"t":"UKR","custom":"Běh na lyžích"},{"name":"Svetlana Anatolyevna Shishkina-Malakhova","y":178,"x":67,"t":"KAZ","custom":"Běh na lyžích"},{"name":"Alyona Viktorovna Sidko","y":170,"x":63,"t":"RUS","custom":"Běh na lyžích"},{"name":"Kaili Sirge","y":172,"x":63,"t":"EST","custom":"Běh na lyžích"},{"name":"Liv Grete Skjelbreid-Poire","y":167,"x":58,"t":"NOR","custom":"Biatlon"},{"name":"Kristina migun-Vhi","y":168,"x":59,"t":"EST","custom":"Běh na lyžích"},{"name":"Chizuru Soneta","y":155,"x":48,"t":"JPN","custom":"Běh na lyžích"},{"name":"Song Bo","y":167,"x":56,"t":"CHN","custom":"Běh na lyžích"},{"name":"Petra Starevi","y":168,"x":61,"t":"CRO","custom":"Biatlon"},{"name":"Darya Yuryevna Starostina","y":168,"x":53,"t":"KAZ","custom":"Běh na lyžích"},{"name":"Rachel Steer","y":173,"x":64,"t":"USA","custom":"Biatlon"},{"name":"Kristin Strmer Steira","y":169,"x":53,"t":"NOR","custom":"Běh na lyžích"},{"name":"Kristin Mrer Stemland","y":168,"x":56,"t":"NOR","custom":"Běh na lyžích"},{"name":"Ccile Storti","y":165,"x":50,"t":"FRA","custom":"Běh na lyžích"},{"name":"Anna-Karin Elisabet Strmstedt","y":173,"x":64,"t":"SWE","custom":"Běh na lyžích"},{"name":"Silja Suija","y":181,"x":70,"t":"EST","custom":"Běh na lyžích"},{"name":"Sun Ribo","y":165,"x":55,"t":"CHN","custom":"Biatlon"},{"name":"Kati Susanna Sundqvist-Venlinen","y":164,"x":58,"t":"FIN","custom":"Běh na lyžích"},{"name":"Tamami Tanaka","y":154,"x":50,"t":"JPN","custom":"Biatlon"},{"name":"Irina Terentjeva","y":168,"x":56,"t":"LTU","custom":"Běh na lyžích"},{"name":"Milaine Thriault","y":167,"x":59,"t":"CAN","custom":"Běh na lyžích"},{"name":"Linda Tjrhom (-Grubben)","y":178,"x":69,"t":"NOR","custom":"Biatlon"},{"name":"Eva Tofalvi","y":172,"x":59,"t":"ROU","custom":"Biatlon"},{"name":"Carolyn Treacy","y":160,"x":59,"t":"USA","custom":"Biatlon"},{"name":"Panagiota Tsakiri","y":172,"x":60,"t":"GRE","custom":"Běh na lyžích"},{"name":"Ikuyo Tsukidate","y":159,"x":53,"t":"JPN","custom":"Biatlon"},{"name":"Sabina Valbusa","y":167,"x":57,"t":"ITA","custom":"Běh na lyžích"},{"name":"Kirsi Maarit Vlimaa (-Antila)","y":167,"x":59,"t":"FIN","custom":"Běh na lyžích"},{"name":"Aleksandra Vasiljevi","y":163,"x":57,"t":"BIH","custom":"Biatlon"},{"name":"Olga Vladimirovna Vasilyonok","y":176,"x":70,"t":"BLR","custom":"Běh na lyžích"},{"name":"Zdeňka Vejnarová","y":168,"x":50,"t":"CZE","custom":"Biatlon"},{"name":"milie Vina","y":161,"x":56,"t":"FRA","custom":"Běh na lyžích"},{"name":"Yelena Vyacheslavovna Volodina-Antonova","y":176,"x":62,"t":"KAZ","custom":"Běh na lyžích"},{"name":"Yevgeniya Voloshenko","y":160,"x":52,"t":"KAZ","custom":"Běh na lyžích"},{"name":"Eva Vrabcová Nývltová","y":162,"x":48,"t":"CZE","custom":"Běh na lyžích"},{"name":"Vedrana Vuievi","y":173,"x":63,"t":"BIH","custom":"Běh na lyžích"},{"name":"Wendy Kay Wagner","y":162,"x":63,"t":"USA","custom":"Běh na lyžích"},{"name":"Wang Chunli","y":165,"x":53,"t":"CHN","custom":"Běh na lyžích"},{"name":"Lindsey Nicole Weier","y":162,"x":61,"t":"USA","custom":"Běh na lyžích"},{"name":"Katarina \"Kati\" Wilhelm","y":173,"x":60,"t":"GER","custom":"Biatlon"},{"name":"Lindsay Ann Williams","y":165,"x":64,"t":"USA","custom":"Běh na lyžích"},{"name":"Xu Yinghui","y":162,"x":54,"t":"CHN","custom":"Běh na lyžích"},{"name":"Vita Mykolavna Yakymchuk","y":168,"x":53,"t":"UKR","custom":"Běh na lyžích"},{"name":"Oksana Aleksandrovna Yatskaya","y":161,"x":54,"t":"KAZ","custom":"Běh na lyžích"},{"name":"Liliya Mykolavna Yefremova (-Vaihina)","y":151,"x":49,"t":"UKR","custom":"Biatlon"},{"name":"Yin Qiao","y":172,"x":62,"t":"CHN","custom":"Biatlon"},{"name":"Sumiko Yokoyama","y":160,"x":53,"t":"JPN","custom":"Běh na lyžích"},{"name":"Tetiana Mykolavna Zavaliy-Antypenko","y":158,"x":52,"t":"UKR","custom":"Běh na lyžích"},{"name":"Olga Viktorovna Zavyalova (Korneyeva-)","y":166,"x":57,"t":"RUS","custom":"Běh na lyžích"},{"name":"Olga Alekseyevna Zaytseva (-Augustin)","y":168,"x":66,"t":"RUS","custom":"Biatlon"},{"name":"Kseniya Pavlovna Zikunkova","y":170,"x":56,"t":"BLR","custom":"Biatlon"},{"name":"Yelena Nikolayevna Zubrilova-Ogurtsova","y":161,"x":52,"t":"BLR","custom":"Biatlon"}]},{"index":5,"showInLegend":true,"name":"Lední hokej","visible":false,"data":[{"name":"Meghan Christina Agosta (-Marciano)","y":168,"x":67,"t":"CAN","custom":"Lední hokej"},{"name":"Nadezhda Valeryevna Aleksandrova","y":172,"x":67,"t":"RUS","custom":"Lední hokej"},{"name":"Cecilia Christine Elisabeth Andersson","y":179,"x":74,"t":"SWE","custom":"Lední hokej"},{"name":"Gunilla Victoria Andersson","y":169,"x":69,"t":"SWE","custom":"Lední hokej"},{"name":"Michela Angeloni","y":167,"x":67,"t":"ITA","custom":"Lední hokej"},{"name":"Gillian Mary Apps","y":180,"x":80,"t":"CAN","custom":"Lední hokej"},{"name":"Jenni Anna Christina Asserholt","y":172,"x":71,"t":"SWE","custom":"Lední hokej"},{"name":"Mariya Mikhaylovna Barykina","y":170,"x":56,"t":"RUS","custom":"Lední hokej"},{"name":"Evelyn Bazzanella","y":168,"x":58,"t":"ITA","custom":"Lední hokej"},{"name":"Maritta Becker","y":168,"x":64,"t":"GER","custom":"Lední hokej"},{"name":"Valentina Bettarini","y":170,"x":66,"t":"ITA","custom":"Lední hokej"},{"name":"Celeste Bissardella","y":166,"x":58,"t":"ITA","custom":"Lední hokej"},{"name":"Jennifer Lori Botterill","y":175,"x":71,"t":"CAN","custom":"Lední hokej"},{"name":"Silvia Bruggmann","y":168,"x":54,"t":"SUI","custom":"Lední hokej"},{"name":"Nicole Bullo","y":160,"x":56,"t":"SUI","custom":"Lední hokej"},{"name":"Tatyana Ivanovna Burina","y":163,"x":68,"t":"RUS","custom":"Lední hokej"},{"name":"Franziska Busch","y":163,"x":69,"t":"GER","custom":"Lední hokej"},{"name":"Yelena Aleksandrovna Byalkovskaya","y":179,"x":78,"t":"RUS","custom":"Lední hokej"},{"name":"Caitlin Kinder Cahow","y":163,"x":68,"t":"USA","custom":"Lední hokej"},{"name":"Heidi Caldart","y":167,"x":56,"t":"ITA","custom":"Lední hokej"},{"name":"Cassie Dawin Campbell (-Pascall)","y":170,"x":66,"t":"CAN","custom":"Lední hokej"},{"name":"Silvia \"Sissi\" Carignano","y":160,"x":59,"t":"ITA","custom":"Lední hokej"},{"name":"Sandra Cattaneo (-Engeli)","y":166,"x":64,"t":"SUI","custom":"Lední hokej"},{"name":"Julie Wu Chu","y":173,"x":67,"t":"USA","custom":"Lední hokej"},{"name":"Diana Da Rugna","y":160,"x":52,"t":"ITA","custom":"Lední hokej"},{"name":"Natalie Rose Darwitz","y":160,"x":65,"t":"USA","custom":"Lední hokej"},{"name":"Anna De la Forest","y":163,"x":47,"t":"ITA","custom":"Lední hokej"},{"name":"Nadia De Nardin","y":170,"x":67,"t":"ITA","custom":"Lední hokej"},{"name":"Linda De Rocco","y":163,"x":52,"t":"ITA","custom":"Lední hokej"},{"name":"Daniela Diaz","y":170,"x":66,"t":"SUI","custom":"Lední hokej"},{"name":"Pamela Kristine \"Pam\" Dreyer (-Sunkinen)","y":165,"x":70,"t":"USA","custom":"Lední hokej"},{"name":"Patricia \"Tricia\" Dunn-Luoma","y":173,"x":66,"t":"USA","custom":"Lední hokej"},{"name":"Ann-Louise Carina Edstrand","y":178,"x":67,"t":"SWE","custom":"Lední hokej"},{"name":"Joa Anna Elisabeth Elfsberg (Engvall-)","y":177,"x":66,"t":"SWE","custom":"Lední hokej"},{"name":"Emma Maria Josefin Eliasson","y":167,"x":68,"t":"SWE","custom":"Lední hokej"},{"name":"Patricia Elsmore-Sautter","y":166,"x":67,"t":"SUI","custom":"Lední hokej"},{"name":"Molly Marie Engstrom","y":175,"x":78,"t":"USA","custom":"Lední hokej"},{"name":"Bettina \"Tina\" Evers","y":167,"x":66,"t":"GER","custom":"Lední hokej"},{"name":"Susanne \"Susi\" Fellner","y":159,"x":57,"t":"GER","custom":"Lední hokej"},{"name":"Gillian Ferrari","y":173,"x":73,"t":"CAN","custom":"Lední hokej"},{"name":"Rebecca Sonia Fiorese","y":162,"x":61,"t":"ITA","custom":"Lední hokej"},{"name":"Sari Kristiina Fisk","y":163,"x":65,"t":"FIN","custom":"Lední hokej"},{"name":"Sabina Florian","y":168,"x":68,"t":"ITA","custom":"Lední hokej"},{"name":"Luana Frasnelli","y":162,"x":54,"t":"ITA","custom":"Lední hokej"},{"name":"Angela Frautschi","y":169,"x":73,"t":"SUI","custom":"Lední hokej"},{"name":"Manuela Friz","y":156,"x":51,"t":"ITA","custom":"Lední hokej"},{"name":"Stephanie \"Steffi\" Frhwirt","y":166,"x":66,"t":"GER","custom":"Lední hokej"},{"name":"Ramona Fuhrer (-Weisskopf)","y":163,"x":68,"t":"SUI","custom":"Lední hokej"},{"name":"Irina Vladimirovna Gashennikova","y":164,"x":66,"t":"RUS","custom":"Lední hokej"},{"name":"Iya Viktorovna Gavrilova","y":170,"x":63,"t":"RUS","custom":"Lední hokej"},{"name":"Yuliya Nikolayevna Gladysheva","y":166,"x":57,"t":"RUS","custom":"Lední hokej"},{"name":"Susann Gtz","y":163,"x":67,"t":"GER","custom":"Lední hokej"},{"name":"Danielle Goyette","y":168,"x":70,"t":"CAN","custom":"Lední hokej"},{"name":"Claudia Grundmann","y":177,"x":69,"t":"GER","custom":"Lední hokej"},{"name":"Chanda Leigh Gunn","y":170,"x":63,"t":"USA","custom":"Lední hokej"},{"name":"Jamie Hagerman","y":175,"x":77,"t":"USA","custom":"Lední hokej"},{"name":"Jennifer \"Jenny\" Har","y":175,"x":65,"t":"GER","custom":"Lední hokej"},{"name":"Maija Johanna Hassinen","y":161,"x":52,"t":"FIN","custom":"Lední hokej"},{"name":"Jayna Hefford","y":163,"x":63,"t":"CAN","custom":"Lední hokej"},{"name":"Satu Inkeri Hoikkala","y":165,"x":63,"t":"FIN","custom":"Lední hokej"},{"name":"Nikola Holmes","y":178,"x":69,"t":"GER","custom":"Lední hokej"},{"name":"Ylva Erika Holst","y":179,"x":82,"t":"SWE","custom":"Lední hokej"},{"name":"Kimberly Michelle \"Kim\" Insalaco (-Legg)","y":165,"x":59,"t":"USA","custom":"Lední hokej"},{"name":"Nanna Kristina Jansson","y":172,"x":67,"t":"SWE","custom":"Lední hokej"},{"name":"Aleksandra Vitalyevna Kapustina","y":166,"x":74,"t":"RUS","custom":"Lední hokej"},{"name":"Waltraud Kaser","y":169,"x":61,"t":"ITA","custom":"Lední hokej"},{"name":"Kathleen Kauth","y":173,"x":68,"t":"USA","custom":"Lední hokej"},{"name":"Rebecca D. \"Becky\" Kellar (-Duke)","y":170,"x":71,"t":"CAN","custom":"Lední hokej"},{"name":"Courtney Kennedy","y":175,"x":86,"t":"USA","custom":"Lední hokej"},{"name":"Alyona Andreyevna Khomich","y":168,"x":53,"t":"RUS","custom":"Lední hokej"},{"name":"Satu Hannele Kiipeli","y":174,"x":72,"t":"FIN","custom":"Lední hokej"},{"name":"Kathryn \"Katie\" King","y":175,"x":77,"t":"USA","custom":"Lední hokej"},{"name":"Kristin King","y":162,"x":61,"t":"USA","custom":"Lední hokej"},{"name":"Gina Kingsbury","y":173,"x":62,"t":"CAN","custom":"Lední hokej"},{"name":"Kati Johanna Kovalainen","y":165,"x":63,"t":"FIN","custom":"Lední hokej"},{"name":"Sabrina Kruck","y":167,"x":62,"t":"GER","custom":"Lední hokej"},{"name":"Ruth Knzle","y":166,"x":65,"t":"SUI","custom":"Lední hokej"},{"name":"Hanna Marjaana Kuoppala","y":179,"x":79,"t":"FIN","custom":"Lední hokej"},{"name":"Emma Kriistina Laaksonen-Terho","y":159,"x":60,"t":"FIN","custom":"Lední hokej"},{"name":"Charline \"Charlie\" Labont","y":175,"x":72,"t":"CAN","custom":"Lední hokej"},{"name":"Andrea Lanzl","y":162,"x":67,"t":"GER","custom":"Lední hokej"},{"name":"Michaela Lanzl","y":158,"x":50,"t":"GER","custom":"Lední hokej"},{"name":"Kathrin Lehmann","y":172,"x":70,"t":"SUI","custom":"Lední hokej"},{"name":"Maria Michaela Leitner","y":161,"x":54,"t":"ITA","custom":"Lední hokej"},{"name":"Monika Leuenberger","y":180,"x":82,"t":"SUI","custom":"Lední hokej"},{"name":"Ylva Maria Lindberg","y":165,"x":73,"t":"SWE","custom":"Lední hokej"},{"name":"Jenny Elisabeth Lindqvist","y":169,"x":68,"t":"SWE","custom":"Lední hokej"},{"name":"Kristina Anna Maria Lundberg","y":172,"x":86,"t":"SWE","custom":"Lední hokej"},{"name":"Carla MacLeod","y":163,"x":63,"t":"CAN","custom":"Lední hokej"},{"name":"Kim Kristine Martin-Hasson","y":166,"x":68,"t":"SWE","custom":"Lední hokej"},{"name":"Jeanette Marty (-Krauer)","y":173,"x":74,"t":"SUI","custom":"Lední hokej"},{"name":"Julia Marty","y":169,"x":69,"t":"SUI","custom":"Lední hokej"},{"name":"Stefanie Marty","y":168,"x":72,"t":"SUI","custom":"Lední hokej"},{"name":"Christine Meier","y":169,"x":68,"t":"SUI","custom":"Lední hokej"},{"name":"Terhi Eveliina Mertanen","y":166,"x":68,"t":"FIN","custom":"Lední hokej"},{"name":"Larisa Sergeyevna Mishina","y":168,"x":73,"t":"RUS","custom":"Lední hokej"},{"name":"Debora Montanari","y":159,"x":58,"t":"ITA","custom":"Lední hokej"},{"name":"Prisca Mosimann","y":184,"x":75,"t":"SUI","custom":"Lední hokej"},{"name":"Frida Margareta Nevalainen","y":165,"x":64,"t":"SWE","custom":"Lední hokej"},{"name":"Emilie Louise O'Konor","y":171,"x":67,"t":"SWE","custom":"Lední hokej"},{"name":"Christina Oswald (-Fellner)","y":172,"x":73,"t":"GER","custom":"Lední hokej"},{"name":"Caroline Ouellette","y":180,"x":77,"t":"CAN","custom":"Lední hokej"},{"name":"Marja-Helena Plvil","y":176,"x":70,"t":"FIN","custom":"Lední hokej"},{"name":"Sarah Sturgis Parsons","y":173,"x":64,"t":"USA","custom":"Lední hokej"},{"name":"Oona Maria Parviainen","y":170,"x":65,"t":"FIN","custom":"Lední hokej"},{"name":"Yekaterina Vladimirovna Pashkevich","y":174,"x":74,"t":"RUS","custom":"Lední hokej"},{"name":"Mari Heini Emilia Pehkonen","y":170,"x":66,"t":"FIN","custom":"Lední hokej"},{"name":"Heidi Marianne Pelttari","y":166,"x":67,"t":"FIN","custom":"Lední hokej"},{"name":"Olga Viktorovna Permyakova","y":171,"x":67,"t":"RUS","custom":"Lední hokej"},{"name":"Kristina Valentinovna Petrovskaya","y":170,"x":64,"t":"RUS","custom":"Lední hokej"},{"name":"Cherie Piper","y":168,"x":76,"t":"CAN","custom":"Lední hokej"},{"name":"Cheryl Pounder (-O'Toole)","y":165,"x":64,"t":"CAN","custom":"Lední hokej"},{"name":"Karoliina Stina Margaretha Rantamki","y":163,"x":65,"t":"FIN","custom":"Lední hokej"},{"name":"Noora Helena Rty","y":165,"x":70,"t":"FIN","custom":"Lední hokej"},{"name":"Sandrine Ray","y":163,"x":60,"t":"SUI","custom":"Lední hokej"},{"name":"Helen Resor","y":178,"x":70,"t":"USA","custom":"Lední hokej"},{"name":"Nina Ritter","y":167,"x":60,"t":"GER","custom":"Lední hokej"},{"name":"Rachel Rochat","y":180,"x":68,"t":"SUI","custom":"Lední hokej"},{"name":"Maria Elisabeth Rooth","y":176,"x":72,"t":"SWE","custom":"Lední hokej"},{"name":"Angela Marie Ruggiero","y":175,"x":86,"t":"USA","custom":"Lední hokej"},{"name":"Laura Ruhnke","y":172,"x":74,"t":"SUI","custom":"Lední hokej"},{"name":"Danijela Kristina Rundqvist","y":178,"x":75,"t":"SWE","custom":"Lední hokej"},{"name":"Mari Susanna Saarinen","y":172,"x":66,"t":"FIN","custom":"Lední hokej"},{"name":"Florence Schelling","y":174,"x":65,"t":"SUI","custom":"Lední hokej"},{"name":"Anja Scheytt","y":174,"x":69,"t":"GER","custom":"Lední hokej"},{"name":"Jennifer Lynn \"Jenny\" Schmidgall-Potter","y":163,"x":66,"t":"USA","custom":"Lední hokej"},{"name":"Tina Schumacher","y":160,"x":60,"t":"SUI","custom":"Lední hokej"},{"name":"Sara Seiler","y":169,"x":65,"t":"GER","custom":"Lední hokej"},{"name":"Zhanna Nikolayevna Shchelchkova","y":164,"x":60,"t":"RUS","custom":"Lední hokej"},{"name":"Eveliina Soile Maarit Simil","y":164,"x":66,"t":"FIN","custom":"Lední hokej"},{"name":"Saija Katariina Sirvi-Tarkki","y":172,"x":60,"t":"FIN","custom":"Lední hokej"},{"name":"Eva Therese Sjlander","y":173,"x":69,"t":"SWE","custom":"Lední hokej"},{"name":"Galina Yuryevna Skiba","y":164,"x":66,"t":"RUS","custom":"Lední hokej"},{"name":"Yekaterina Vyacheslavovna Smolentseva","y":176,"x":64,"t":"RUS","custom":"Lední hokej"},{"name":"Yekaterina Anatolyevna Smolina","y":164,"x":54,"t":"RUS","custom":"Lední hokej"},{"name":"Denise Soesilo","y":167,"x":50,"t":"GER","custom":"Lední hokej"},{"name":"Colleen Sostorics","y":163,"x":76,"t":"CAN","custom":"Lední hokej"},{"name":"Tatyana Yuryevna Sotnikova","y":167,"x":59,"t":"RUS","custom":"Lední hokej"},{"name":"Katharina Sparer","y":163,"x":52,"t":"ITA","custom":"Lední hokej"},{"name":"Kim St-Pierre","y":175,"x":71,"t":"CAN","custom":"Lední hokej"},{"name":"Kelly Stephens (-Tysland)","y":167,"x":59,"t":"USA","custom":"Lední hokej"},{"name":"Vicky Sunohara","y":170,"x":75,"t":"CAN","custom":"Lední hokej"},{"name":"Nora Tallus (-Liikanen)","y":158,"x":66,"t":"FIN","custom":"Lední hokej"},{"name":"Jenny Tamas","y":173,"x":63,"t":"GER","custom":"Lední hokej"},{"name":"Anna Katarina Timglas","y":168,"x":62,"t":"SWE","custom":"Lední hokej"},{"name":"Silvia Toffano","y":163,"x":52,"t":"ITA","custom":"Lední hokej"},{"name":"Svetlana Rudolfovna Trefilova","y":173,"x":67,"t":"RUS","custom":"Lední hokej"},{"name":"Oksana Vitalyevna Tretyakova","y":164,"x":78,"t":"RUS","custom":"Lední hokej"},{"name":"Saara Elisa Tuominen","y":169,"x":65,"t":"FIN","custom":"Lední hokej"},{"name":"Satu Sinikka Tuominen","y":163,"x":61,"t":"FIN","custom":"Lední hokej"},{"name":"Sarah Marie Vaillancourt","y":168,"x":63,"t":"CAN","custom":"Lední hokej"},{"name":"Sabrina Viel","y":166,"x":53,"t":"ITA","custom":"Lední hokej"},{"name":"Ingrid Anna Kristina Vikman","y":168,"x":74,"t":"SWE","custom":"Lední hokej"},{"name":"Lyndsay Wall","y":173,"x":65,"t":"USA","custom":"Lední hokej"},{"name":"Stephanie Wartosch-Krten","y":172,"x":69,"t":"GER","custom":"Lední hokej"},{"name":"Katherine Marie \"Katie\" Weatherston","y":163,"x":66,"t":"CAN","custom":"Lední hokej"},{"name":"Kristen Elizabeth \"Krissy\" Wendell (-Pohl)","y":167,"x":70,"t":"USA","custom":"Lední hokej"},{"name":"Hayley Marie Wickenheiser","y":178,"x":77,"t":"CAN","custom":"Lední hokej"},{"name":"Pernilla Margareta Stephanie Winberg","y":165,"x":63,"t":"SWE","custom":"Lední hokej"},{"name":"Raffaela \"Raffi\" Wolf","y":168,"x":65,"t":"GER","custom":"Lední hokej"}]},{"index":6,"showInLegend":true,"name":"Alpské lyžování","visible":false,"data":[{"name":"Brigitte Acton (-Smith)","y":168,"x":63,"t":"CAN","custom":"Alpské lyžování"},{"name":"Neha Ahuja","y":162,"x":54,"t":"IND","custom":"Alpské lyžování"},{"name":"Chimene Mary \"Chemmy\" Alcott (-Crawford)","y":169,"x":69,"t":"GBR","custom":"Alpské lyžování"},{"name":"Olesya Murtazaliyevna Aliyeva","y":169,"x":60,"t":"RUS","custom":"Alpské lyžování"},{"name":"Daniela Anguita Loux","y":162,"x":58,"t":"CHI","custom":"Alpské lyžování"},{"name":"Mirella Silva Prado Arnhold","y":159,"x":51,"t":"BRA","custom":"Alpské lyžování"},{"name":"Franziska Christine \"Frnzi\" Aufdenblatten","y":173,"x":68,"t":"SUI","custom":"Alpské lyžování"},{"name":"Noelle Barahona Neder","y":171,"x":65,"t":"CHI","custom":"Alpské lyžování"},{"name":"Anne-Sophie Barthet","y":170,"x":71,"t":"FRA","custom":"Alpské lyžování"},{"name":"Nike Lovisa Bent","y":164,"x":73,"t":"SWE","custom":"Alpské lyžování"},{"name":"Macarena Benvenuto Gutirrez","y":162,"x":56,"t":"CHI","custom":"Alpské lyžování"},{"name":"Monika Bergmann-Schmuderer","y":176,"x":74,"t":"GER","custom":"Alpské lyžování"},{"name":"Sylviane Berthod","y":166,"x":65,"t":"SUI","custom":"Alpské lyžování"},{"name":"Therese Kristina Borssn","y":173,"x":65,"t":"SWE","custom":"Alpské lyžování"},{"name":"Emily Brydon","y":181,"x":90,"t":"CAN","custom":"Alpské lyžování"},{"name":"Nicola Jane Campbell","y":164,"x":71,"t":"NZL","custom":"Alpské lyžování"},{"name":"Andrea Casasnovas Rocha","y":165,"x":70,"t":"ESP","custom":"Alpské lyžování"},{"name":"Daniela Ceccarelli","y":168,"x":60,"t":"ITA","custom":"Alpské lyžování"},{"name":"Annalisa Ceresa","y":176,"x":75,"t":"ITA","custom":"Alpské lyžování"},{"name":"Kirsten Lee Clark (-Rickenbach)","y":167,"x":66,"t":"USA","custom":"Alpské lyžování"},{"name":"Alexandra Coletti","y":164,"x":60,"t":"MON","custom":"Alpské lyžování"},{"name":"Stacey Janelle Cook","y":163,"x":73,"t":"USA","custom":"Alpské lyžování"},{"name":"Chiara Costazza","y":172,"x":64,"t":"ITA","custom":"Alpské lyžování"},{"name":"Florine de Leymarie","y":176,"x":65,"t":"FRA","custom":"Alpské lyžování"},{"name":"Dong Jinzhi","y":170,"x":66,"t":"CHN","custom":"Alpské lyžování"},{"name":"Michaela Dorfmeister","y":172,"x":72,"t":"AUT","custom":"Alpské lyžování"},{"name":"Christelle Laura Douibi","y":169,"x":59,"t":"ALG","custom":"Alpské lyžování"},{"name":"Ana Drev","y":171,"x":60,"t":"SLO","custom":"Alpské lyžování"},{"name":"Martina Maria Ertl-Renz","y":162,"x":59,"t":"GER","custom":"Alpské lyžování"},{"name":"Elena Fanchini","y":164,"x":69,"t":"ITA","custom":"Alpské lyžování"},{"name":"Nadia Fanchini","y":164,"x":65,"t":"ITA","custom":"Alpské lyžování"},{"name":"Matea Ferk","y":165,"x":62,"t":"CRO","custom":"Alpské lyžování"},{"name":"Andrea Fischbacher","y":164,"x":58,"t":"AUT","custom":"Alpské lyžování"},{"name":"Nika Fleiss","y":167,"x":63,"t":"CRO","custom":"Alpské lyžování"},{"name":"Jana Gantnerov","y":165,"x":65,"t":"SVK","custom":"Alpské lyžování"},{"name":"Annemarie Gerg","y":174,"x":68,"t":"GER","custom":"Alpské lyžování"},{"name":"Elisabeth Grgl","y":167,"x":66,"t":"AUT","custom":"Alpské lyžování"},{"name":"Renate Gtschl","y":165,"x":68,"t":"AUT","custom":"Alpské lyžování"},{"name":"Petra Haltmayr","y":166,"x":62,"t":"GER","custom":"Alpské lyžování"},{"name":"Janette Helene Hargin","y":168,"x":65,"t":"SWE","custom":"Alpské lyžování"},{"name":"Noriyo Hiroi","y":161,"x":63,"t":"JPN","custom":"Alpské lyžování"},{"name":"Mizue Hoshi","y":157,"x":61,"t":"JPN","custom":"Alpské lyžování"},{"name":"Nicole Hosp","y":174,"x":70,"t":"AUT","custom":"Alpské lyžování"},{"name":"Lucie Hrstková","y":163,"x":63,"t":"CZE","custom":"Alpské lyžování"},{"name":"Eva Hukov","y":167,"x":62,"t":"SVK","custom":"Alpské lyžování"},{"name":"Ivana Ivchevska","y":164,"x":59,"t":"MKD","custom":"Alpské lyžování"},{"name":"Ingrid Jacquemod","y":176,"x":70,"t":"FRA","custom":"Alpské lyžování"},{"name":"Ana Jelui","y":165,"x":60,"t":"CRO","custom":"Alpské lyžování"},{"name":"Magdalini \"Magda\" Kalomoirou","y":170,"x":70,"t":"GRE","custom":"Alpské lyžování"},{"name":"Katarzyna Karasiska","y":172,"x":66,"t":"POL","custom":"Alpské lyžování"},{"name":"Denise Karbon","y":160,"x":58,"t":"ITA","custom":"Alpské lyžování"},{"name":"Lindsey Caroline Kildow-Vonn","y":178,"x":75,"t":"USA","custom":"Alpské lyžování"},{"name":"Michaela Kirchgasser","y":169,"x":62,"t":"AUT","custom":"Alpské lyžování"},{"name":"Mariya Kirkova","y":165,"x":59,"t":"BUL","custom":"Alpské lyžování"},{"name":"Ana Kobal","y":167,"x":61,"t":"SLO","custom":"Alpské lyžování"},{"name":"Janica Kosteli","y":175,"x":76,"t":"CRO","custom":"Alpské lyžování"},{"name":"Kristina Lyn Koznick","y":169,"x":75,"t":"USA","custom":"Alpské lyžování"},{"name":"Dagn Linda Kristjnsdttir","y":161,"x":63,"t":"ISL","custom":"Alpské lyžování"},{"name":"Dagmara Krzyyska","y":167,"x":66,"t":"POL","custom":"Alpské lyžování"},{"name":"Eva Kurfirstová","y":163,"x":59,"t":"CZE","custom":"Alpské lyžování"},{"name":"Sherry Lawrence","y":171,"x":63,"t":"CAN","custom":"Alpské lyžování"},{"name":"Jessica Monika Lindell Vikarby","y":169,"x":69,"t":"SWE","custom":"Alpské lyžování"},{"name":"Jelena Lolovi","y":167,"x":59,"t":"SCG","custom":"Alpské lyžování"},{"name":"Libby Ludlow","y":160,"x":62,"t":"USA","custom":"Alpské lyžování"},{"name":"Christina Lustenberger","y":173,"x":64,"t":"CAN","custom":"Alpské lyžování"},{"name":"Soa Maculov","y":165,"x":58,"t":"SVK","custom":"Alpské lyžování"},{"name":"Julia Marie Mancuso (-Fish)","y":168,"x":64,"t":"USA","custom":"Alpské lyžování"},{"name":"Marie Marchand-Arvier (-Jay)","y":164,"x":65,"t":"FRA","custom":"Alpské lyžování"},{"name":"Klementina \"Tina\" Maze","y":172,"x":68,"t":"SLO","custom":"Alpské lyžování"},{"name":"Kirsten Kate Llewellyn \"Kirsty\" McGarry","y":172,"x":65,"t":"IRL","custom":"Alpské lyžování"},{"name":"Erika Louise McLeod","y":173,"x":72,"t":"NZL","custom":"Alpské lyžování"},{"name":"Alexandra Meissnitzer","y":165,"x":62,"t":"AUT","custom":"Alpské lyžování"},{"name":"Daniela Merighetti","y":168,"x":66,"t":"ITA","custom":"Alpské lyžování"},{"name":"Manuela Mlgg","y":170,"x":62,"t":"ITA","custom":"Alpské lyžování"},{"name":"Carole Montillet-Carles","y":164,"x":73,"t":"FRA","custom":"Alpské lyžování"},{"name":"Leire Morlans Aguilar","y":170,"x":65,"t":"ESP","custom":"Alpské lyžování"},{"name":"Bianca Andreea Narea","y":164,"x":63,"t":"ROU","custom":"Alpské lyžování"},{"name":"Chirine Njeim","y":168,"x":60,"t":"LIB","custom":"Alpské lyžování"},{"name":"Tiiu Nurmberg","y":160,"x":60,"t":"EST","custom":"Alpské lyžování"},{"name":"O Jae-Eun","y":164,"x":55,"t":"KOR","custom":"Alpské lyžování"},{"name":"Anna Helene Ottosson (-Blixth)","y":165,"x":64,"t":"SWE","custom":"Alpské lyžování"},{"name":"Anja Sofia Tess Prson","y":170,"x":81,"t":"SWE","custom":"Alpské lyžování"},{"name":"Laure Pequegnot","y":168,"x":63,"t":"FRA","custom":"Alpské lyžování"},{"name":"Maria Helena Pietil Holmner","y":170,"x":63,"t":"SWE","custom":"Alpské lyžování"},{"name":"Tanja Tuulia Poutiainen (-Rinne)","y":170,"x":65,"t":"FIN","custom":"Alpské lyžování"},{"name":"Karen Putzer","y":161,"x":59,"t":"ITA","custom":"Alpské lyžování"},{"name":"Urka Rabi","y":168,"x":74,"t":"SLO","custom":"Alpské lyžování"},{"name":"Henna Karoliina Raita","y":173,"x":67,"t":"FIN","custom":"Alpské lyžování"},{"name":"Mojca Rataj","y":168,"x":60,"t":"BIH","custom":"Alpské lyžování"},{"name":"Lucia Recchia (-Wieser)","y":171,"x":69,"t":"ITA","custom":"Alpské lyžování"},{"name":"Kaylin Lorraine Richardson","y":178,"x":68,"t":"USA","custom":"Alpské lyžování"},{"name":"Mara Jos Rienda Contreras","y":167,"x":66,"t":"ESP","custom":"Alpské lyžování"},{"name":"Petra Robnik","y":179,"x":78,"t":"SLO","custom":"Alpské lyžování"},{"name":"Shona Rubens","y":170,"x":78,"t":"CAN","custom":"Alpské lyžování"},{"name":"Carolina Vernica Ruiz Castillo","y":165,"x":63,"t":"ESP","custom":"Alpské lyžování"},{"name":"Marlies Schild (-Raich)","y":172,"x":66,"t":"AUT","custom":"Alpské lyžování"},{"name":"Martina Schild","y":170,"x":67,"t":"SUI","custom":"Alpské lyžování"},{"name":"Sarah Kathryn Schleper (-de Gaxiola)","y":162,"x":61,"t":"USA","custom":"Alpské lyžování"},{"name":"Mami Sekizuka","y":159,"x":55,"t":"JPN","custom":"Alpské lyžování"},{"name":"Genevive Simard","y":170,"x":66,"t":"CAN","custom":"Alpské lyžování"},{"name":"Macarena Mara Simari Birkner","y":168,"x":60,"t":"ARG","custom":"Alpské lyžování"},{"name":"Mara Beln Simari Birkner","y":168,"x":60,"t":"ARG","custom":"Alpské lyžování"},{"name":"Wendy Siorpaes","y":167,"x":59,"t":"ITA","custom":"Alpské lyžování"},{"name":"Yuliya Siparenko","y":170,"x":65,"t":"UKR","custom":"Alpské lyžování"},{"name":"Resi Frances Stiegler","y":173,"x":61,"t":"USA","custom":"Alpské lyžování"},{"name":"Nadia Styger (-Hrlimann)","y":171,"x":70,"t":"SUI","custom":"Alpské lyžování"},{"name":"Marija Trmi","y":173,"x":64,"t":"SCG","custom":"Alpské lyžování"},{"name":"Rka Tuss","y":167,"x":61,"t":"HUN","custom":"Alpské lyžování"},{"name":"Duygu Gl Ulusoy","y":163,"x":70,"t":"TUR","custom":"Alpské lyžování"},{"name":"Kelly Vanderbeek","y":173,"x":66,"t":"CAN","custom":"Alpské lyžování"},{"name":"Miriam Vzquez","y":170,"x":65,"t":"ARG","custom":"Alpské lyžování"},{"name":"Vanessa Vidal","y":168,"x":64,"t":"FRA","custom":"Alpské lyžování"},{"name":"Jessica Walter","y":162,"x":63,"t":"LIE","custom":"Alpské lyžování"},{"name":"Christina \"Tina\" Weirather","y":162,"x":61,"t":"LIE","custom":"Alpské lyžování"},{"name":"Vera Yeremenko","y":170,"x":60,"t":"KAZ","custom":"Alpské lyžování"},{"name":"Šárka Strachová (Záhrobská)","y":174,"x":66,"t":"CZE","custom":"Alpské lyžování"},{"name":"Petra Zakouřilová","y":170,"x":68,"t":"CZE","custom":"Alpské lyžování"},{"name":"Kathrin Zettel","y":167,"x":61,"t":"AUT","custom":"Alpské lyžování"},{"name":"Veronika Zuzulov (-Velez)","y":172,"x":72,"t":"SVK","custom":"Alpské lyžování"}]},{"index":7,"showInLegend":true,"name":"Saně + Skeleton","visible":false,"data":[{"name":"Lindsay Alcock","y":170,"x":68,"t":"CAN","custom":"Skeleton"},{"name":"Yuliya Igorevna Anashkina","y":172,"x":70,"t":"RUS","custom":"Saně"},{"name":"Aiva Aparjode","y":177,"x":74,"t":"LAT","custom":"Saně"},{"name":"Desire Bjerke Andersen","y":172,"x":61,"t":"NOR","custom":"Skeleton"},{"name":"Hannah Campbell-Pegg","y":169,"x":70,"t":"AUS","custom":"Saně"},{"name":"Louise Mary Elizabeth \"Lou\" Corcoran","y":180,"x":68,"t":"NZL","custom":"Skeleton"},{"name":"Michelle Despain (-Hoeger)","y":160,"x":55,"t":"ARG","custom":"Saně"},{"name":"Alex Gough","y":171,"x":70,"t":"CAN","custom":"Saně"},{"name":"Veronika Halder","y":165,"x":62,"t":"AUT","custom":"Saně"},{"name":"Erin Mullady Hamlin","y":170,"x":65,"t":"USA","custom":"Saně"},{"name":"Madoka Harada","y":163,"x":68,"t":"JPN","custom":"Saně"},{"name":"Mellisa Hollingsworth-Richards","y":167,"x":58,"t":"CAN","custom":"Skeleton"},{"name":"Anja Huber (-Selbach)","y":172,"x":60,"t":"GER","custom":"Skeleton"},{"name":"Tatjana Hfner","y":178,"x":76,"t":"GER","custom":"Saně"},{"name":"Markéta Jeriová","y":172,"x":70,"t":"CZE","custom":"Saně"},{"name":"Martina Kocher","y":172,"x":60,"t":"SUI","custom":"Saně"},{"name":"Silke Kraushaar (-Pielach)","y":177,"x":66,"t":"GER","custom":"Saně"},{"name":"Regan Lauscher","y":174,"x":70,"t":"CAN","custom":"Saně"},{"name":"Liliya Anatolivna Ludan","y":170,"x":90,"t":"UKR","custom":"Saně"},{"name":"Sonja Manzenreiter","y":163,"x":65,"t":"AUT","custom":"Saně"},{"name":"Tanja Morel","y":164,"x":58,"t":"SUI","custom":"Skeleton"},{"name":"Eiko Nakayama","y":160,"x":55,"t":"JPN","custom":"Skeleton"},{"name":"Anastasia Oberstolz-Antonova","y":170,"x":67,"t":"ITA","custom":"Saně"},{"name":"Anna Orlova","y":175,"x":84,"t":"LAT","custom":"Saně"},{"name":"Sylke Otto","y":170,"x":64,"t":"GER","custom":"Saně"},{"name":"Maya Pedersen (Bieri-)","y":163,"x":54,"t":"SUI","custom":"Skeleton"},{"name":"Sarah Podorieszach","y":162,"x":61,"t":"ITA","custom":"Saně"},{"name":"Nina Reithmayer","y":171,"x":66,"t":"AUT","custom":"Saně"},{"name":"Samantha \"Sam\" Retrosi","y":167,"x":57,"t":"USA","custom":"Saně"},{"name":"Aleksandra Vasilyevna Rodionova","y":172,"x":66,"t":"RUS","custom":"Saně"},{"name":"Shelley-Marie Rudman","y":171,"x":55,"t":"GBR","custom":"Skeleton"},{"name":"Veronika Sabolov","y":168,"x":60,"t":"SVK","custom":"Saně"},{"name":"Diana Sartor","y":178,"x":64,"t":"GER","custom":"Skeleton"},{"name":"Meaghan Simister","y":171,"x":68,"t":"CAN","custom":"Saně"},{"name":"Jana iajov","y":167,"x":63,"t":"SVK","custom":"Saně"},{"name":"Anastasiya Valeryevna Skulkina (-Tambotvseva)","y":179,"x":62,"t":"RUS","custom":"Saně"},{"name":"Ewelina Joanna Staszulonek","y":170,"x":60,"t":"POL","custom":"Saně"},{"name":"Michelle Steele","y":164,"x":55,"t":"AUS","custom":"Skeleton"},{"name":"Maija Truma","y":173,"x":67,"t":"LAT","custom":"Saně"},{"name":"Svetlana Valeryevna Trunova","y":167,"x":60,"t":"RUS","custom":"Skeleton"},{"name":"Katie Uhlaender","y":160,"x":61,"t":"USA","custom":"Skeleton"},{"name":"Monika Izabela Woowiec","y":169,"x":62,"t":"POL","custom":"Skeleton"},{"name":"Nataliya Vasylivna Yakushenko","y":174,"x":78,"t":"UKR","custom":"Saně"},{"name":"Courtney Zablocki","y":165,"x":61,"t":"USA","custom":"Saně"},{"name":"Costanza Zanoletti","y":173,"x":59,"t":"ITA","custom":"Skeleton"}]},{"index":8,"showInLegend":true,"name":"Akrobatické lyžování + Snowboarding","visible":false,"data":[{"name":"Ccile Alzina","y":160,"x":50,"t":"FRA","custom":"Snowboarding"},{"name":"Dborah Jessica Anthonioz","y":165,"x":52,"t":"FRA","custom":"Snowboarding"},{"name":"Shannon Deanne Bahrke","y":162,"x":55,"t":"USA","custom":"Akrobatické lyžování"},{"name":"Veronika Elisabeth Bauer","y":165,"x":62,"t":"CAN","custom":"Akrobatické lyžování"},{"name":"Nina Bednarik","y":160,"x":61,"t":"SLO","custom":"Akrobatické lyžování"},{"name":"Manuela Berchtold","y":164,"x":58,"t":"AUS","custom":"Akrobatické lyžování"},{"name":"Ingrid Kristine Berntsen","y":161,"x":59,"t":"NOR","custom":"Akrobatické lyžování"},{"name":"Isabelle Blanc","y":171,"x":75,"t":"FRA","custom":"Snowboarding"},{"name":"Gretchen Bleiler","y":165,"x":57,"t":"USA","custom":"Snowboarding"},{"name":"Corinna Boccacini","y":171,"x":90,"t":"ITA","custom":"Snowboarding"},{"name":"Svetlana Sergeyevna Boldykova","y":165,"x":64,"t":"RUS","custom":"Snowboarding"},{"name":"Juliane Linda Bray","y":167,"x":70,"t":"NZL","custom":"Snowboarding"},{"name":"Torah Jane Bright (-Thomson)","y":161,"x":57,"t":"AUS","custom":"Snowboarding"},{"name":"Kendall Brown","y":153,"x":43,"t":"NZL","custom":"Snowboarding"},{"name":"Ursula Bruhin","y":166,"x":66,"t":"SUI","custom":"Snowboarding"},{"name":"Kjersti stgrd Buaas","y":161,"x":57,"t":"NOR","custom":"Snowboarding"},{"name":"Alisa Peta Camplin (-Warner)","y":157,"x":49,"t":"AUS","custom":"Akrobatické lyžování"},{"name":"Queralt Castellet Ibez","y":156,"x":52,"t":"ESP","custom":"Snowboarding"},{"name":"Marina Yevgenyevna Cherkasova","y":164,"x":62,"t":"RUS","custom":"Akrobatické lyžování"},{"name":"Isabel Clark Ribeiro","y":167,"x":61,"t":"BRA","custom":"Snowboarding"},{"name":"Kelly Clark","y":163,"x":61,"t":"USA","custom":"Snowboarding"},{"name":"Sarah Conrad","y":162,"x":58,"t":"CAN","custom":"Snowboarding"},{"name":"Emily Cook","y":160,"x":52,"t":"USA","custom":"Akrobatické lyžování"},{"name":"Jacqueline \"Jacqui\" Cooper","y":176,"x":65,"t":"AUS","custom":"Akrobatické lyžování"},{"name":"Holly Crawford","y":173,"x":63,"t":"AUS","custom":"Snowboarding"},{"name":"Isabella Dal Balcon","y":165,"x":60,"t":"ITA","custom":"Snowboarding"},{"name":"Maria Elisabeth Danielsson (-Hoback)","y":168,"x":70,"t":"SWE","custom":"Snowboarding"},{"name":"Tania Detomas","y":165,"x":55,"t":"ITA","custom":"Snowboarding"},{"name":"Nadiya Viktorivna Didenko","y":168,"x":65,"t":"UKR","custom":"Akrobatické lyžování"},{"name":"Deidra Rae Dionne","y":164,"x":57,"t":"CAN","custom":"Akrobatické lyžování"},{"name":"Lyudmila Vyacheslavovna Dymchenko","y":158,"x":43,"t":"RUS","custom":"Akrobatické lyžování"},{"name":"Petra Elsterová","y":175,"x":58,"t":"CZE","custom":"Snowboarding"},{"name":"Sara Ingrid Fischer","y":167,"x":65,"t":"SWE","custom":"Snowboarding"},{"name":"Gabrielle Rose \"Rosey\" Fletcher","y":175,"x":68,"t":"USA","custom":"Snowboarding"},{"name":"Kate Foster","y":178,"x":76,"t":"GBR","custom":"Snowboarding"},{"name":"Mellie Francon","y":168,"x":57,"t":"SUI","custom":"Snowboarding"},{"name":"Tanja Frieden","y":173,"x":65,"t":"SUI","custom":"Snowboarding"},{"name":"Yuka Fujimori","y":160,"x":55,"t":"JPN","custom":"Snowboarding"},{"name":"Chikako Fushimi","y":154,"x":47,"t":"JPN","custom":"Snowboarding"},{"name":"Elizabeth \"Liz\" Gardner","y":157,"x":55,"t":"AUS","custom":"Akrobatické lyžování"},{"name":"Zo Gillings (-Brier)","y":170,"x":65,"t":"GBR","custom":"Snowboarding"},{"name":"Olga Mikhaylovna Golovanova","y":162,"x":58,"t":"RUS","custom":"Snowboarding"},{"name":"Michelle Gorgone","y":160,"x":77,"t":"USA","custom":"Snowboarding"},{"name":"Doris Gnther","y":165,"x":58,"t":"AUT","custom":"Snowboarding"},{"name":"Guo Xinxin","y":157,"x":60,"t":"CHN","custom":"Akrobatické lyžování"},{"name":"Aprilia Emilie Maria Hgglf (-Biveson)","y":164,"x":58,"t":"SWE","custom":"Snowboarding"},{"name":"Miyuki Hatanaka","y":153,"x":54,"t":"JPN","custom":"Akrobatické lyžování"},{"name":"Jennifer Heil","y":162,"x":56.5,"t":"CAN","custom":"Akrobatické lyžování"},{"name":"Kayo Henmi","y":158,"x":51,"t":"JPN","custom":"Akrobatické lyžování"},{"name":"Elena Hight","y":157,"x":52,"t":"USA","custom":"Snowboarding"},{"name":"Katharina Himmler","y":155,"x":68,"t":"GER","custom":"Snowboarding"},{"name":"Lydia Ierodiaconou-Lassila","y":157,"x":54,"t":"AUS","custom":"Akrobatické lyžování"},{"name":"Mero Imai","y":154,"x":48,"t":"JPN","custom":"Snowboarding"},{"name":"Blanka Isielonis","y":163,"x":58,"t":"POL","custom":"Snowboarding"},{"name":"Miki Ito","y":162,"x":53,"t":"JPN","custom":"Akrobatické lyžování"},{"name":"Lindsey Jacobellis","y":168,"x":64,"t":"USA","custom":"Snowboarding"},{"name":"Hannah Angela Kearney","y":168,"x":69,"t":"USA","custom":"Akrobatické lyžování"},{"name":"Sara Lisbet Kjellin","y":169,"x":64,"t":"SWE","custom":"Akrobatické lyžování"},{"name":"Amelie Kober","y":168,"x":56,"t":"GER","custom":"Snowboarding"},{"name":"Olga Yuryevna Korolyova","y":165,"x":64,"t":"RUS","custom":"Akrobatické lyžování"},{"name":"Tetiana Valerivna Kozachenko","y":165,"x":62,"t":"UKR","custom":"Akrobatické lyžování"},{"name":"Doresia Krings","y":160,"x":55,"t":"AUT","custom":"Snowboarding"},{"name":"Heidi Krings","y":168,"x":50,"t":"AUT","custom":"Snowboarding"},{"name":"Marie Laissus","y":173,"x":65,"t":"FRA","custom":"Snowboarding"},{"name":"Sandra Laoura","y":167,"x":60,"t":"FRA","custom":"Akrobatické lyžování"},{"name":"Evelyne Leu","y":167,"x":62,"t":"SUI","custom":"Akrobatické lyžování"},{"name":"Li Nina","y":160,"x":52,"t":"CHN","custom":"Akrobatické lyžování"},{"name":"Paulina Magdalena Ligocka","y":169,"x":64,"t":"POL","custom":"Snowboarding"},{"name":"Jana Lindsey","y":170,"x":64,"t":"USA","custom":"Akrobatické lyžování"},{"name":"Alexa Loo (-Goosen)","y":168,"x":60,"t":"CAN","custom":"Snowboarding"},{"name":"Cheryl Maas","y":174,"x":66,"t":"NED","custom":"Snowboarding"},{"name":"Dominique Maltais","y":178,"x":71,"t":"CAN","custom":"Snowboarding"},{"name":"Margarita Marbler (Olejnikova-)","y":157,"x":50,"t":"AUT","custom":"Akrobatické lyžování"},{"name":"Jagna Marczuajtis (Kolasiska-)","y":171,"x":64,"t":"POL","custom":"Snowboarding"},{"name":"Romina Masolini","y":160,"x":50,"t":"ITA","custom":"Snowboarding"},{"name":"Lesley McKenna","y":160,"x":57,"t":"GBR","custom":"Snowboarding"},{"name":"Daniela Meuli","y":183,"x":74,"t":"SUI","custom":"Snowboarding"},{"name":"Nuria Montan Ubeda","y":162,"x":56,"t":"ESP","custom":"Akrobatické lyžování"},{"name":"Manuela Mller","y":163,"x":58,"t":"SUI","custom":"Akrobatické lyžování"},{"name":"Shiho Nakashima","y":156,"x":44,"t":"JPN","custom":"Snowboarding"},{"name":"Mercedes Nicoll","y":163,"x":58,"t":"CAN","custom":"Snowboarding"},{"name":"Olivia Nobs","y":170,"x":58,"t":"SUI","custom":"Snowboarding"},{"name":"Anna-Kristina Olofsson","y":171,"x":67,"t":"SWE","custom":"Snowboarding"},{"name":"Pan Lei","y":164,"x":48,"t":"CHN","custom":"Snowboarding"},{"name":"Mariangela Fabiana Parravicini","y":158,"x":50,"t":"ITA","custom":"Akrobatické lyžování"},{"name":"Manuela Laura Pesko","y":170,"x":56,"t":"SUI","custom":"Snowboarding"},{"name":"Amber Peterson","y":167,"x":68,"t":"CAN","custom":"Akrobatické lyžování"},{"name":"Julie Pomagalski","y":161,"x":60,"t":"FRA","custom":"Snowboarding"},{"name":"Marion Posch","y":164,"x":64,"t":"ITA","custom":"Snowboarding"},{"name":"Mariya Aleksandrovna Prusakova","y":165,"x":53,"t":"RUS","custom":"Snowboarding"},{"name":"Carmen Ranigler","y":166,"x":59,"t":"ITA","custom":"Snowboarding"},{"name":"Kristi Richards","y":157,"x":57,"t":"CAN","custom":"Akrobatické lyžování"},{"name":"Malle Danica Ricker","y":169,"x":63,"t":"CAN","custom":"Snowboarding"},{"name":"Manuela Riegler","y":169,"x":62,"t":"AUT","custom":"Snowboarding"},{"name":"Michelle Roark","y":152,"x":48,"t":"USA","custom":"Akrobatické lyžování"},{"name":"Audrey Robichaud","y":155,"x":59,"t":"CAN","custom":"Akrobatické lyžování"},{"name":"Yuliya Sergeyevna Rodionova","y":176,"x":59,"t":"KAZ","custom":"Akrobatické lyžování"},{"name":"Sophie Rodriguez","y":168,"x":57,"t":"FRA","custom":"Snowboarding"},{"name":"Karine Martine Ruby","y":165,"x":61,"t":"FRA","custom":"Snowboarding"},{"name":"Darya Vladimirovna Rybalova","y":162,"x":57,"t":"KAZ","custom":"Akrobatické lyžování"},{"name":"Niina Katriina Sarias","y":164,"x":72,"t":"FIN","custom":"Snowboarding"},{"name":"Tae Satoya","y":166,"x":55,"t":"JPN","custom":"Akrobatické lyžování"},{"name":"Lotte Nicolien Sauerbreij","y":164,"x":58,"t":"NED","custom":"Snowboarding"},{"name":"Deborah Scanzio","y":170,"x":65,"t":"ITA","custom":"Akrobatické lyžování"},{"name":"Darya Yevgenyevna Serova","y":160,"x":55,"t":"RUS","custom":"Akrobatické lyžování"},{"name":"Johanna \"Joh\" Shaw","y":173,"x":66,"t":"AUS","custom":"Snowboarding"},{"name":"Erin Simmons","y":165,"x":58,"t":"CAN","custom":"Snowboarding"},{"name":"Assol Vitalyevna Slivets","y":168,"x":64,"t":"BLR","custom":"Akrobatické lyžování"},{"name":"Stphanie St-Pierre","y":157,"x":58,"t":"CAN","custom":"Akrobatické lyžování"},{"name":"Nikola Sudová","y":162,"x":56,"t":"CZE","custom":"Akrobatické lyžování"},{"name":"Šárka Sudová","y":160,"x":46,"t":"CZE","custom":"Akrobatické lyžování"},{"name":"Sun Zhifeng","y":158,"x":58,"t":"CHN","custom":"Snowboarding"},{"name":"Tomoka Takeuchi","y":165,"x":61,"t":"JPN","custom":"Snowboarding"},{"name":"Hannah Lee Teter","y":170,"x":60,"t":"USA","custom":"Snowboarding"},{"name":"Emily Thomas","y":170,"x":64,"t":"AUS","custom":"Snowboarding"},{"name":"Kari Traa","y":168,"x":65,"t":"NOR","custom":"Akrobatické lyžování"},{"name":"Alla Petrovna Tsuper","y":153,"x":53,"t":"BLR","custom":"Akrobatické lyžování"},{"name":"Yekaterina Nikolayevna Tudegesheva","y":162,"x":65,"t":"RUS","custom":"Snowboarding"},{"name":"Aiko Uemura","y":156,"x":51,"t":"JPN","custom":"Akrobatické lyžování"},{"name":"Dominique Valle","y":168,"x":57,"t":"CAN","custom":"Snowboarding"},{"name":"Doriane Monique Vidal","y":168,"x":56,"t":"FRA","custom":"Snowboarding"},{"name":"Clara Villoslada Pinto","y":170,"x":61,"t":"ESP","custom":"Snowboarding"},{"name":"Svetlana Olegovna Vinogradova","y":168,"x":59,"t":"RUS","custom":"Snowboarding"},{"name":"Jillian Rachelle Vogtli","y":165,"x":64,"t":"USA","custom":"Akrobatické lyžování"},{"name":"Olha Volodymyrivna Volkova","y":160,"x":52,"t":"UKR","custom":"Akrobatické lyžování"},{"name":"Wang He","y":157,"x":53,"t":"CHN","custom":"Akrobatické lyžování"},{"name":"Xu Nannan","y":158,"x":53,"t":"CHN","custom":"Akrobatické lyžování"},{"name":"Soko Yamaoka","y":162,"x":53,"t":"JPN","custom":"Snowboarding"},{"name":"Eri Yanetani","y":171,"x":67,"t":"JPN","custom":"Snowboarding"},{"name":"Yun Chae-Rin","y":164,"x":50,"t":"KOR","custom":"Akrobatické lyžování"},{"name":"Aleksandra Viktorova Zhekova","y":167,"x":63,"t":"BUL","custom":"Snowboarding"},{"name":"Anna Vladislavovna Zukal","y":168,"x":60,"t":"RUS","custom":"Akrobatické lyžování"}]},{"index":9,"showInLegend":true,"name":"Curling","visible":false,"data":[{"name":"Eleonora Alver","y":169,"x":61,"t":"ITA","custom":"Curling"},{"name":"Glenys Bakker","y":170,"x":73,"t":"CAN","custom":"Curling"},{"name":"Binia Beeli (-Feltscher)","y":175,"x":62,"t":"SUI","custom":"Curling"},{"name":"Maureen Brunt (-Clark)","y":160,"x":74,"t":"USA","custom":"Curling"},{"name":"Violetta Caldart (-Siorpaes)","y":172,"x":61,"t":"ITA","custom":"Curling"},{"name":"Lynn Cameron","y":167,"x":60,"t":"GBR","custom":"Curling"},{"name":"Denise Kanstrup Dupont","y":169,"x":68,"t":"DEN","custom":"Curling"},{"name":"Yekaterina Vladimirovna Galkina","y":170,"x":58,"t":"RUS","custom":"Curling"},{"name":"Diana Gaspari","y":169,"x":64,"t":"ITA","custom":"Curling"},{"name":"Courtney Christine George","y":155,"x":52,"t":"USA","custom":"Curling"},{"name":"Marianne Haslum","y":182,"x":67,"t":"NOR","custom":"Curling"},{"name":"Yumie Hayashi-Funayama","y":153,"x":45,"t":"JPN","custom":"Curling"},{"name":"Dorthe Elisabeth Holm","y":169,"x":65,"t":"DEN","custom":"Curling"},{"name":"Camilla Holth","y":168,"x":52,"t":"NOR","custom":"Curling"},{"name":"Sandra Jenkins (Rippel-)","y":173,"x":59,"t":"CAN","custom":"Curling"},{"name":"Cassandra Lynn \"Cassie\" Johnson (-Potter)","y":170,"x":55,"t":"USA","custom":"Curling"},{"name":"Jamie Victoria Johnson (-Haskell)","y":170,"x":61,"t":"USA","custom":"Curling"},{"name":"Christine Keshen","y":168,"x":61,"t":"CAN","custom":"Curling"},{"name":"Shannon Kleibrink","y":169,"x":69,"t":"CAN","custom":"Curling"},{"name":"Deborah \"Debbie\" Knox","y":167,"x":66,"t":"GBR","custom":"Curling"},{"name":"Malene Krause (-Larsen)","y":165,"x":72,"t":"DEN","custom":"Curling"},{"name":"Giulia Lacedelli","y":165,"x":59,"t":"ITA","custom":"Curling"},{"name":"Eva Cathrine Lindahl (Norberg-)","y":163,"x":64,"t":"SWE","custom":"Curling"},{"name":"Jacqueline \"Jackie\" Lockhart (Steele-)","y":177,"x":70,"t":"GBR","custom":"Curling"},{"name":"Eva Maria Lund (-Eriksson)","y":169,"x":66,"t":"SWE","custom":"Curling"},{"name":"Rhona Martin (Howie-)","y":167,"x":71,"t":"GBR","custom":"Curling"},{"name":"Moe Meguro","y":162,"x":53,"t":"JPN","custom":"Curling"},{"name":"Michle Moser (Knobel-)","y":175,"x":72,"t":"SUI","custom":"Curling"},{"name":"Mari Motohashi","y":160,"x":61,"t":"JPN","custom":"Curling"},{"name":"Yana Anatolyevna Nekrasova","y":178,"x":62,"t":"RUS","custom":"Curling"},{"name":"Lene Nielsen","y":177,"x":58,"t":"DEN","custom":"Curling"},{"name":"Amy Nixon (-Westlund)","y":157,"x":54,"t":"CAN","custom":"Curling"},{"name":"Anette Charlotte Norberg","y":174,"x":70,"t":"SWE","custom":"Curling"},{"name":"Dordi Agathe Nordby","y":164,"x":56,"t":"NOR","custom":"Curling"},{"name":"Ayumi Onodera-Ogasawara","y":156,"x":51,"t":"JPN","custom":"Curling"},{"name":"Mirjam Ott","y":162,"x":58,"t":"SUI","custom":"Curling"},{"name":"Rosa Pompanin","y":174,"x":58,"t":"ITA","custom":"Curling"},{"name":"Lyudmila Andreyevna Privivkova","y":168,"x":57,"t":"RUS","custom":"Curling"},{"name":"Marianne Cecilie Lydersen Rrvik","y":161,"x":55,"t":"NOR","custom":"Curling"},{"name":"Jessica Schultz","y":163,"x":60,"t":"USA","custom":"Curling"},{"name":"Valeria Claudia Splty","y":169,"x":64,"t":"SUI","custom":"Curling"},{"name":"Anna Maria Svrd-Le Moine (Bergstrm-)","y":165,"x":59,"t":"SWE","custom":"Curling"},{"name":"Sakurako Terada","y":162,"x":57,"t":"JPN","custom":"Curling"},{"name":"Kelly Wood (-Schafer)","y":154,"x":58,"t":"GBR","custom":"Curling"},{"name":"Nkeiruka Khilariyevna Yezekh","y":178,"x":75,"t":"RUS","custom":"Curling"},{"name":"Olga Nikolayevna Zharkova","y":168,"x":60,"t":"RUS","custom":"Curling"}]},{"index":10,"showInLegend":false,"name":"Alpinismus","visible":false,"data":[]}]}